{"ttl":0,"data":[{"_id":"64ea599edbe6a10bf2ada64f","calculation":{"id":"1000002601","result":675941.0327229885,"additional":[{"name":"E Avg DMG","value":19888.63816553699,"quantity":1,"type":"E"},{"name":"E Avg DMG","value":21923.628417214793,"quantity":1,"type":"E"},{"name":"NA Avg DMG","value":3835.538046071736,"quantity":1,"type":"NA"},{"name":"Collision Plunge Avg DMG","value":13306.761871421835,"quantity":1,"type":"P"},{"name":"High Plunge Avg DMG","value":33235.644975839816,"quantity":1,"type":"P"},{"name":"NA Avg DMG","value":4288.060318568524,"quantity":1,"type":"NA"},{"name":"Collision Plunge Avg DMG","value":14711.034590150664,"quantity":1,"type":"P"},{"name":"High Plunge Avg DMG","value":36743.027912417594,"quantity":1,"type":"P"},{"name":"Collision Plunge Avg DMG","value":16115.307308879492,"quantity":1,"type":"P"},{"name":"High Plunge Avg DMG","value":41065.8567712361,"quantity":1,"type":"P"},{"name":"Collision Plunge Avg DMG","value":16441.792464024435,"quantity":1,"type":"P"},{"name":"High Plunge Avg DMG","value":41065.8567712361,"quantity":1,"type":"P"},{"name":"Collision Plunge Avg DMG","value":16441.792464024435,"quantity":1,"type":"P"},{"name":"High Plunge Avg DMG","value":41065.8567712361,"quantity":1,"type":"P"},{"name":"Collision Plunge Avg DMG","value":16441.792464024435,"quantity":1,"type":"P"},{"name":"High Plunge Avg DMG","value":41881.30269347682,"quantity":1,"type":"P"},{"name":"Collision Plunge Avg DMG","value":16768.277619169377,"quantity":1,"type":"P"},{"name":"High Plunge Avg DMG","value":41881.30269347682,"quantity":1,"type":"P"},{"name":"Collision Plunge Avg DMG","value":16768.277619169377,"quantity":1,"type":"P"},{"name":"High Plunge Avg DMG","value":41881.30269347682,"quantity":1,"type":"P"},{"name":"Collision Plunge Avg DMG","value":17094.762774314317,"quantity":1,"type":"P"},{"name":"High Plunge Avg DMG","value":42696.748615717544,"quantity":1,"type":"P"},{"name":"Collision Plunge Avg DMG","value":17094.762774314317,"quantity":1,"type":"P"},{"name":"High Plunge Avg DMG","value":42696.748615717544,"quantity":1,"type":"P"},{"name":"Collision Plunge Avg DMG","value":17094.762774314317,"quantity":1,"type":"P"},{"name":"High Plunge Avg DMG","value":43512.19453795827,"quantity":1,"type":"P"}]},"characterId":10000026,"type":"current","uid":"704113135","artifactObjects":{"EQUIP_SHOES":{"mainStatKey":"ATK%"},"EQUIP_RING":{"mainStatKey":"Anemo DMG Bonus"},"EQUIP_DRESS":{"mainStatKey":"Crit DMG"}},"artifactSets":{"Marechaussee Hunter":{"icon":"https://enka.network/ui/UI_RelicIcon_15031_4.png","count":4},"Emblem of Severed Fate":{"icon":"https://enka.network/ui/UI_RelicIcon_15020_4.png","count":1}},"constellation":0,"costumeId":"","critValue":223.88999913307646,"md5":"e95e914da16d99914bbee1fc9383fa63","name":"Xiao","owner":{"nickname":"DovahKiato","adventureRank":60.0000004595,"profilePicture":{"characterId":10000024,"id":"","assets":{"icon":"UI_AvatarIcon_Beidou","sideIcon":"UI_AvatarIcon_Side_Beidou","gachaIcon":"UI_Gacha_AvatarImg_Beidou","constellations":["UI_Talent_S_Beidou_02","UI_Talent_S_Beidou_01","UI_Talent_U_Beidou_01","UI_Talent_S_Beidou_03","UI_Talent_U_Beidou_02","UI_Talent_S_Beidou_04"],"talents":{"normalAttack":"Skill_A_04","elementalSkill":"Skill_S_Beidou_01","elementalBurst":"Skill_E_Beidou_01"},"costumes":[]},"name":null},"nameCard":"UI_NameCardPic_TheatreMechanicus_P","patreon":{},"region":"EU","enkaOwner":{}},"propMap":{"ascension":{"val":"5"},"level":{"val":"80"}},"proudSkillExtraLevelMap":{},"stats":{"maxHp":{"value":21138.406674371727},"atk":{"value":2490.9769514604504},"def":{"value":857.5652647681655},"elementalMastery":{"value":0},"energyRecharge":{"value":1.233200019146962},"healingBonus":{"value":0},"critRate":{"value":0.6347000213321142},"critDamage":{"value":2.615000009810536},"anemoDamageBonus":{"value":0.466000007799}},"talentsLevelMap":{"normalAttacks":{"icon":"https://enka.network/ui/Skill_A_03.png","level":8,"rawLevel":8,"id":10261,"boosted":false},"elementalSkill":{"icon":"https://enka.network/ui/Skill_S_Xiao_01.png","level":8,"rawLevel":8,"id":10262,"boosted":false},"elementalBurst":{"icon":"https://enka.network/ui/Skill_E_Xiao_01.png","level":8,"rawLevel":8,"id":10265,"boosted":false}},"weapon":{"weaponInfo":{"level":90,"promoteLevel":6,"refinementLevel":{"value":0}},"flat":{"icon":{"value":"UI_EquipIcon_Pole_Homa"}},"name":"Staff of Homa","icon":"https://enka.network/ui/UI_EquipIcon_Pole_Homa_Awaken.png"},"lastBuildUpdate":1729515005310,"sortableType":"xiao","icon":"https://enka.network/ui/UI_AvatarIcon_Xiao.png","index":341,"nameCardLink":"https://enka.network/ui/UI_NameCardPic_TheatreMechanicus_P.png","profilePictureLink":"https://enka.network/ui/UI_AvatarIcon_Beidou.png","characterMetadata":{"element":"Anemo"}},{"_id":"65bbea34dbe6a10bf28cef77","calculation":{"id":"1000002601","result":675748.1956484902,"additional":null},"characterId":10000026,"type":"current","uid":"701877420","artifactObjects":{"EQUIP_SHOES":{"mainStatKey":"ATK%"},"EQUIP_RING":{"mainStatKey":"Anemo DMG Bonus"},"EQUIP_DRESS":{"mainStatKey":"Crit RATE"}},"artifactSets":{"Vermillion Hereafter":{"icon":"https://enka.network/ui/UI_RelicIcon_15023_4.png","count":4},"Golden Troupe":{"icon":"https://enka.network/ui/UI_RelicIcon_15032_4.png","count":1}},"constellation":1,"costumeId":"","critValue":238.6699970757118,"md5":"9355abdbaa15a0ffa1c31bb7ca36d85f","name":"Xiao","owner":{"nickname":"Vathoss","adventureRank":60.0000000781,"profilePicture":{"characterId":0,"id":6800,"assets":{"icon":"UI_AvatarIcon_Linette_Circle","oldIcon":"UI_AvatarIcon_Linette"},"name":null},"nameCard":"UI_NameCardPic_Linette_P","patreon":{},"region":"EU","enkaOwner":{}},"propMap":{"ascension":{"val":"6"},"level":{"val":"90"}},"proudSkillExtraLevelMap":{},"stats":{"maxHp":{"value":21418.6539964353},"atk":{"value":2456.294544718706},"def":{"value":815.4965816590188},"elementalMastery":{"value":16.32000054952422},"energyRecharge":{"value":1.3886000311712718},"healingBonus":{"value":0},"critRate":{"value":1.0041000358496792},"critDamage":{"value":2.024000008854736},"anemoDamageBonus":{"value":0.466000009715}},"talentsLevelMap":{"normalAttacks":{"icon":"https://enka.network/ui/Skill_A_03.png","level":10,"rawLevel":10,"id":10261,"boosted":false},"elementalSkill":{"icon":"https://enka.network/ui/Skill_S_Xiao_01.png","level":10,"rawLevel":10,"id":10262,"boosted":false},"elementalBurst":{"icon":"https://enka.network/ui/Skill_E_Xiao_01.png","level":10,"rawLevel":10,"id":10265,"boosted":false}},"weapon":{"weaponInfo":{"level":90,"promoteLevel":6,"refinementLevel":{"value":0}},"flat":{"icon":{"value":"UI_EquipIcon_Pole_Homa"}},"name":"Staff of Homa","icon":"https://enka.network/ui/UI_EquipIcon_Pole_Homa_Awaken.png"},"icon":"https://enka.network/ui/UI_AvatarIcon_Xiao.png","index":342,"nameCardLink":"https://enka.network/ui/UI_NameCardPic_Linette_P.png","profilePictureLink":"https://enka.network/ui/UI_AvatarIcon_Linette.png","characterMetadata":{"element":"Anemo"}},{"_id":"667010448f1b3f627f957986","calculation":{"id":"1000002601","result":675600.0814166864,"additional":[{"name":"E Avg DMG","value":22382.546208275653,"quantity":1,"type":"E"},{"name":"E Avg DMG","value":24672.711227567124,"quantity":1,"type":"E"},{"name":"NA Avg DMG","value":4192.2279021317045,"quantity":1,"type":"NA"},{"name":"Collision Plunge Avg DMG","value":14306.39605545698,"quantity":1,"type":"P"},{"name":"High Plunge Avg DMG","value":35732.38213603938,"quantity":1,"type":"P"},{"name":"NA Avg DMG","value":4499.862876369234,"quantity":1,"type":"NA"},{"name":"Collision Plunge Avg DMG","value":14812.735426973695,"quantity":1,"type":"P"},{"name":"High Plunge Avg DMG","value":36997.041093013795,"quantity":1,"type":"P"},{"name":"Collision Plunge Avg DMG","value":15319.074798490412,"quantity":1,"type":"P"},{"name":"High Plunge Avg DMG","value":40327.136132496096,"quantity":1,"type":"P"},{"name":"Collision Plunge Avg DMG","value":16146.02628778914,"quantity":1,"type":"P"},{"name":"High Plunge Avg DMG","value":40327.136132496096,"quantity":1,"type":"P"},{"name":"Collision Plunge Avg DMG","value":16146.02628778914,"quantity":1,"type":"P"},{"name":"High Plunge Avg DMG","value":40327.136132496096,"quantity":1,"type":"P"},{"name":"Collision Plunge Avg DMG","value":16146.02628778914,"quantity":1,"type":"P"},{"name":"High Plunge Avg DMG","value":41127.913258029526,"quantity":1,"type":"P"},{"name":"Collision Plunge Avg DMG","value":16466.638405571157,"quantity":1,"type":"P"},{"name":"High Plunge Avg DMG","value":41127.913258029526,"quantity":1,"type":"P"},{"name":"Collision Plunge Avg DMG","value":16466.638405571157,"quantity":1,"type":"P"},{"name":"High Plunge Avg DMG","value":41127.913258029526,"quantity":1,"type":"P"},{"name":"Collision Plunge Avg DMG","value":16787.250523353166,"quantity":1,"type":"P"},{"name":"High Plunge Avg DMG","value":41928.69038356297,"quantity":1,"type":"P"},{"name":"Collision Plunge Avg DMG","value":16787.250523353166,"quantity":1,"type":"P"},{"name":"High Plunge Avg DMG","value":41928.69038356297,"quantity":1,"type":"P"},{"name":"Collision Plunge Avg DMG","value":16787.250523353166,"quantity":1,"type":"P"},{"name":"High Plunge Avg DMG","value":42729.467509096416,"quantity":1,"type":"P"}]},"characterId":10000026,"type":"current","uid":"804249920","artifactObjects":{"EQUIP_SHOES":{"mainStatKey":"ATK%"},"EQUIP_RING":{"mainStatKey":"Anemo DMG Bonus"},"EQUIP_DRESS":{"mainStatKey":"Crit DMG"}},"artifactSets":{"Vermillion Hereafter":{"icon":"https://enka.network/ui/UI_RelicIcon_15023_4.png","count":4},"Echoes of an Offering":{"icon":"https://enka.network/ui/UI_RelicIcon_15024_4.png","count":1}},"constellation":0,"costumeId":"","critValue":237.1399980988207,"lastBuildUpdate":1722931426336,"md5":"864cf573bea9a3d30239ea2b3a86543e","name":"Xiao","owner":{"nickname":"MeoMeo","adventureRank":60.0000001145,"profilePicture":{"characterId":0,"id":100160,"assets":{"icon":"UI_AvatarIcon_71100_Circle","oldIcon":"UI_AvatarIcon_71100_Circle"},"name":null},"nameCard":"UI_NameCardPic_Chenyu1_P","patreon":{},"region":"ASIA","enkaOwner":{}},"propMap":{"ascension":{"val":"6"},"level":{"val":"90"}},"proudSkillExtraLevelMap":{},"sortableType":"xiao","stats":{"maxHp":{"value":21593.88931072733},"atk":{"value":2532.4289665721067},"def":{"value":799.2965448000001},"elementalMastery":{"value":18.649999971330274},"energyRecharge":{"value":1.2395000236528835},"healingBonus":{"value":0},"critRate":{"value":0.8136000239564063},"critDamage":{"value":2.389700011746395},"anemoDamageBonus":{"value":0.466000005659}},"talentsLevelMap":{"normalAttacks":{"icon":"https://enka.network/ui/Skill_A_03.png","level":8,"rawLevel":8,"id":10261,"boosted":false},"elementalSkill":{"icon":"https://enka.network/ui/Skill_S_Xiao_01.png","level":8,"rawLevel":8,"id":10262,"boosted":false},"elementalBurst":{"icon":"https://enka.network/ui/Skill_E_Xiao_01.png","level":10,"rawLevel":10,"id":10265,"boosted":false}},"weapon":{"weaponInfo":{"level":90,"promoteLevel":6,"refinementLevel":{"value":0}},"flat":{"icon":{"value":"UI_EquipIcon_Pole_Homa"}},"name":"Staff of Homa","icon":"https://enka.network/ui/UI_EquipIcon_Pole_Homa_Awaken.png"},"icon":"https://enka.network/ui/UI_AvatarIcon_Xiao.png","index":343,"nameCardLink":"https://enka.network/ui/UI_NameCardPic_Chenyu1_P.png","profilePictureLink":"https://enka.network/ui/UI_AvatarIcon_71100_Circle.png","characterMetadata":{"element":"Anemo"}},{"_id":"64ea58cedbe6a10bf2a95c67","calculation":{"id":"1000002601","result":675555.3717517866,"additional":[{"name":"E Avg DMG","value":22422.987577986376,"quantity":1,"type":"E"},{"name":"E Avg DMG","value":24717.290534868433,"quantity":1,"type":"E"},{"name":"NA Avg DMG","value":4198.02955699408,"quantity":1,"type":"NA"},{"name":"Collision Plunge Avg DMG","value":14319.113519853057,"quantity":1,"type":"P"},{"name":"High Plunge Avg DMG","value":35764.145921680465,"quantity":1,"type":"P"},{"name":"NA Avg DMG","value":4501.787930216345,"quantity":1,"type":"NA"},{"name":"Collision Plunge Avg DMG","value":14819.072356365406,"quantity":1,"type":"P"},{"name":"High Plunge Avg DMG","value":37012.86853003679,"quantity":1,"type":"P"},{"name":"Collision Plunge Avg DMG","value":15319.031192877752,"quantity":1,"type":"P"},{"name":"High Plunge Avg DMG","value":40310.76580779948,"quantity":1,"type":"P"},{"name":"Collision Plunge Avg DMG","value":16139.47199908332,"quantity":1,"type":"P"},{"name":"High Plunge Avg DMG","value":40310.76580779948,"quantity":1,"type":"P"},{"name":"Collision Plunge Avg DMG","value":16139.47199908332,"quantity":1,"type":"P"},{"name":"High Plunge Avg DMG","value":40310.76580779948,"quantity":1,"type":"P"},{"name":"Collision Plunge Avg DMG","value":16139.47199908332,"quantity":1,"type":"P"},{"name":"High Plunge Avg DMG","value":41111.21786884951,"quantity":1,"type":"P"},{"name":"Collision Plunge Avg DMG","value":16459.953968776543,"quantity":1,"type":"P"},{"name":"High Plunge Avg DMG","value":41111.21786884951,"quantity":1,"type":"P"},{"name":"Collision Plunge Avg DMG","value":16459.953968776543,"quantity":1,"type":"P"},{"name":"High Plunge Avg DMG","value":41111.21786884951,"quantity":1,"type":"P"},{"name":"Collision Plunge Avg DMG","value":16780.435938469756,"quantity":1,"type":"P"},{"name":"High Plunge Avg DMG","value":41911.66992989955,"quantity":1,"type":"P"},{"name":"Collision Plunge Avg DMG","value":16780.435938469756,"quantity":1,"type":"P"},{"name":"High Plunge Avg DMG","value":41911.66992989955,"quantity":1,"type":"P"},{"name":"Collision Plunge Avg DMG","value":16780.435938469756,"quantity":1,"type":"P"},{"name":"High Plunge Avg DMG","value":42712.1219909496,"quantity":1,"type":"P"}]},"characterId":10000026,"type":"current","uid":"725484201","artifactObjects":{"EQUIP_SHOES":{"mainStatKey":"ATK%"},"EQUIP_RING":{"mainStatKey":"Anemo DMG Bonus"},"EQUIP_DRESS":{"mainStatKey":"Crit DMG"}},"artifactSets":{"Vermillion Hereafter":{"icon":"https://enka.network/ui/UI_RelicIcon_15023_4.png","count":4},"Bloodstained Chivalry":{"icon":"https://enka.network/ui/UI_RelicIcon_15008_4.png","count":1}},"constellation":0,"costumeId":"","critValue":241.78999800306028,"md5":"edcedaea8617637ec2701e0b80fcbe9c","name":"Xiao","owner":{"nickname":"Traumwandler","adventureRank":60.0000001627,"profilePicture":{"characterId":0,"id":8700,"assets":{"icon":"UI_AvatarIcon_Kinich_Circle","oldIcon":"UI_AvatarIcon_Kinich"},"name":null},"nameCard":"UI_NameCardPic_Sethos_P","patreon":{},"region":"EU","enkaOwner":{}},"propMap":{"ascension":{"val":"6"},"level":{"val":"89"}},"proudSkillExtraLevelMap":{},"stats":{"maxHp":{"value":20630.526669227715},"atk":{"value":2569.382188061668},"def":{"value":909.9991213328985},"elementalMastery":{"value":34.97000004715449},"energyRecharge":{"value":1.3238000122104208},"healingBonus":{"value":0},"critRate":{"value":0.7359000166801063},"critDamage":{"value":2.591600002616391},"anemoDamageBonus":{"value":0.466000000832}},"talentsLevelMap":{"normalAttacks":{"icon":"https://enka.network/ui/Skill_A_03.png","level":10,"rawLevel":10,"id":10261,"boosted":false},"elementalSkill":{"icon":"https://enka.network/ui/Skill_S_Xiao_01.png","level":10,"rawLevel":10,"id":10262,"boosted":false},"elementalBurst":{"icon":"https://enka.network/ui/Skill_E_Xiao_01.png","level":10,"rawLevel":10,"id":10265,"boosted":false}},"weapon":{"weaponInfo":{"level":90,"promoteLevel":6,"refinementLevel":{"value":0}},"flat":{"icon":{"value":"UI_EquipIcon_Pole_Homa"}},"name":"Staff of Homa","icon":"https://enka.network/ui/UI_EquipIcon_Pole_Homa_Awaken.png"},"lastBuildUpdate":1723704719705,"sortableType":"xiao","icon":"https://enka.network/ui/UI_AvatarIcon_Xiao.png","index":344,"nameCardLink":"https://enka.network/ui/UI_NameCardPic_Sethos_P.png","profilePictureLink":"https://enka.network/ui/UI_AvatarIcon_Kinich.png","characterMetadata":{"element":"Anemo"}},{"_id":"64ea5950dbe6a10bf2ac0c71","calculation":{"id":"1000002601","result":675519.6610422123,"additional":null},"characterId":10000026,"type":"current","uid":"801580770","artifactObjects":{"EQUIP_SHOES":{"mainStatKey":"ATK%"},"EQUIP_RING":{"mainStatKey":"Anemo DMG Bonus"},"EQUIP_DRESS":{"mainStatKey":"Crit RATE"}},"artifactSets":{"Vermillion Hereafter":{"icon":"https://enka.network/ui/UI_RelicIcon_15023_4.png","count":4},"Blizzard Strayer":{"icon":"https://enka.network/ui/UI_RelicIcon_14001_4.png","count":1}},"constellation":1,"costumeId":"","critValue":244.05999697070553,"md5":"8d50b67ae0ef9812d8d29dada5733cf2","name":"Xiao","owner":{"nickname":"青ねぎ","adventureRank":60.0000004633,"profilePicture":{"characterId":0,"id":4501,"assets":{"icon":"UI_AvatarIcon_ShenheCostumeDai_Circle","oldIcon":"UI_AvatarIcon_ShenheCostumeDai_Circle"},"name":null},"nameCard":"UI_NameCardPic_Ganyu_P","patreon":{},"region":"ASIA","enkaOwner":{}},"propMap":{"ascension":{"val":"6"},"level":{"val":"90"}},"proudSkillExtraLevelMap":{},"stats":{"maxHp":{"value":20062.897206845777},"atk":{"value":2460.1664150976426},"def":{"value":903.7655734896803},"elementalMastery":{"value":0},"energyRecharge":{"value":1.3238000101717111},"healingBonus":{"value":0},"critRate":{"value":0.83690001593467},"critDamage":{"value":2.4122999859296916},"anemoDamageBonus":{"value":0.466000005859}},"talentsLevelMap":{"normalAttacks":{"icon":"https://enka.network/ui/Skill_A_03.png","level":10,"rawLevel":10,"id":10261,"boosted":false},"elementalSkill":{"icon":"https://enka.network/ui/Skill_S_Xiao_01.png","level":10,"rawLevel":10,"id":10262,"boosted":false},"elementalBurst":{"icon":"https://enka.network/ui/Skill_E_Xiao_01.png","level":10,"rawLevel":10,"id":10265,"boosted":false}},"weapon":{"weaponInfo":{"level":90,"promoteLevel":6,"refinementLevel":{"value":0}},"flat":{"icon":{"value":"UI_EquipIcon_Pole_Homa"}},"name":"Staff of Homa","icon":"https://enka.network/ui/UI_EquipIcon_Pole_Homa_Awaken.png"},"icon":"https://enka.network/ui/UI_AvatarIcon_Xiao.png","index":345,"nameCardLink":"https://enka.network/ui/UI_NameCardPic_Ganyu_P.png","profilePictureLink":"https://enka.network/ui/UI_AvatarIcon_ShenheCostumeDai_Circle.png","characterMetadata":{"element":"Anemo"}},{"_id":"65a6369ddbe6a10bf285eafd","calculation":{"id":"1000002601","result":675494.3741031992},"characterId":10000026,"type":"current","uid":"803891743","artifactObjects":{"EQUIP_SHOES":{"mainStatKey":"ATK%"},"EQUIP_RING":{"mainStatKey":"Anemo DMG Bonus"},"EQUIP_DRESS":{"mainStatKey":"Crit RATE"}},"artifactSets":{"Vermillion Hereafter":{"icon":"https://enka.network/ui/UI_RelicIcon_15023_4.png","count":4},"Tenacity of the Millelith":{"icon":"https://enka.network/ui/UI_RelicIcon_15017_4.png","count":1}},"constellation":1,"costumeId":"","critValue":218.43999742959056,"md5":"1287cd4a196a7141f1df6ef725e34f39","name":"Xiao","owner":{"nickname":"空","adventureRank":57.0000001956,"profilePicture":{"characterId":0,"id":2800,"assets":{"icon":"UI_AvatarIcon_Xiao_Circle","oldIcon":"UI_AvatarIcon_Xiao"},"name":null},"nameCard":"UI_NameCardPic_Furina_P","patreon":{},"region":"ASIA"},"propMap":{"ascension":{"val":"6"},"level":{"val":"90"}},"proudSkillExtraLevelMap":{},"stats":{"maxHp":{"value":20062.897207540278},"atk":{"value":2700.9986911516476},"def":{"value":957.6135524435847},"elementalMastery":{"value":0},"energyRecharge":{"value":1.2267000223339162},"healingBonus":{"value":0},"critRate":{"value":0.7980000319247792},"critDamage":{"value":2.2339000060623238},"anemoDamageBonus":{"value":0.466000009964}},"talentsLevelMap":{"normalAttacks":{"icon":"https://enka.network/ui/Skill_A_03.png","level":10,"rawLevel":10,"id":10261,"boosted":false},"elementalSkill":{"icon":"https://enka.network/ui/Skill_S_Xiao_01.png","level":10,"rawLevel":10,"id":10262,"boosted":false},"elementalBurst":{"icon":"https://enka.network/ui/Skill_E_Xiao_01.png","level":10,"rawLevel":10,"id":10265,"boosted":false}},"weapon":{"weaponInfo":{"level":80,"promoteLevel":5,"refinementLevel":{"value":0}},"flat":{"icon":{"value":"UI_EquipIcon_Pole_Proto"}},"name":"Prototype Starglitter","icon":"https://enka.network/ui/UI_EquipIcon_Pole_Proto_Awaken.png"},"icon":"https://enka.network/ui/UI_AvatarIcon_Xiao.png","index":346,"nameCardLink":"https://enka.network/ui/UI_NameCardPic_Furina_P.png","profilePictureLink":"https://enka.network/ui/UI_AvatarIcon_Xiao.png","characterMetadata":{"element":"Anemo"}},{"_id":"64ea598bdbe6a10bf2ad4da5","calculation":{"id":"1000002601","result":675454.1415001026},"characterId":10000026,"type":"current","uid":"801084138","artifactObjects":{"EQUIP_SHOES":{"mainStatKey":"ATK%"},"EQUIP_RING":{"mainStatKey":"Anemo DMG Bonus"},"EQUIP_DRESS":{"mainStatKey":"Crit RATE"}},"artifactSets":{"Vermillion Hereafter":{"icon":"https://enka.network/ui/UI_RelicIcon_15023_4.png","count":4},"Maiden Beloved":{"icon":"https://enka.network/ui/UI_RelicIcon_14004_4.png","count":1}},"constellation":0,"costumeId":"","critValue":224.66999829302327,"md5":"83d4bf969ffd146c3b5e986cb82b26c4","name":"Xiao","owner":{"nickname":"て","adventureRank":58,"profilePicture":10000026,"nameCard":"UI_NameCardPic_Xiao_P","patreon":{},"region":"ASIA"},"propMap":{"ascension":{"val":"6"},"level":{"val":"90"}},"proudSkillExtraLevelMap":{},"stats":{"maxHp":{"value":20062.897207455877},"atk":{"value":2597.787126790626},"def":{"value":799.2965799245794},"elementalMastery":{"value":39.6300003285666},"energyRecharge":{"value":1.220200022031451},"healingBonus":{"value":0},"critRate":{"value":0.8874000302553617},"critDamage":{"value":2.1174000151604857},"anemoDamageBonus":{"value":0.466000009399}},"talentsLevelMap":{"normalAttacks":{"icon":"https://enka.network/ui/Skill_A_03.png","level":10,"rawLevel":10,"id":10261,"boosted":false},"elementalSkill":{"icon":"https://enka.network/ui/Skill_S_Xiao_01.png","level":10,"rawLevel":10,"id":10262,"boosted":false},"elementalBurst":{"icon":"https://enka.network/ui/Skill_E_Xiao_01.png","level":10,"rawLevel":10,"id":10265,"boosted":false}},"weapon":{"weaponInfo":{"level":90,"promoteLevel":6,"refinementLevel":{"value":0}},"flat":{"icon":{"value":"UI_EquipIcon_Pole_Homa"}},"name":"Staff of Homa","icon":"https://enka.network/ui/UI_EquipIcon_Pole_Homa_Awaken.png"},"icon":"https://enka.network/ui/UI_AvatarIcon_Xiao.png","index":347,"nameCardLink":"https://enka.network/ui/UI_NameCardPic_Xiao_P.png","profilePictureLink":"https://enka.network/ui/UI_AvatarIcon_Xiao.png","characterMetadata":{"element":"Anemo"}},{"_id":"64ea5932dbe6a10bf2ab7322","calculation":{"id":"1000002601","result":675344.2092916443},"characterId":10000026,"type":"current","uid":"828045187","artifactObjects":{"EQUIP_SHOES":{"mainStatKey":"ATK%"},"EQUIP_RING":{"mainStatKey":"Anemo DMG Bonus"},"EQUIP_DRESS":{"mainStatKey":"Crit DMG"}},"artifactSets":{"Vermillion Hereafter":{"icon":"https://enka.network/ui/UI_RelicIcon_15023_4.png","count":4},"Echoes of an Offering":{"icon":"https://enka.network/ui/UI_RelicIcon_15024_4.png","count":1}},"constellation":3,"costumeId":"","critValue":232.45999815960764,"md5":"fd50258892b5b7f468825e12516b4092","name":"Xiao","owner":{"nickname":"こどもは風の子","adventureRank":59.0000001995,"profilePicture":{"characterId":10000026,"id":"","assets":{"icon":"UI_AvatarIcon_Xiao","sideIcon":"UI_AvatarIcon_Side_Xiao","gachaIcon":"UI_Gacha_AvatarImg_Xiao","constellations":["UI_Talent_S_Xiao_01","UI_Talent_S_Xiao_02","UI_Talent_U_Xiao_01","UI_Talent_S_Xiao_03","UI_Talent_U_Xiao_02","UI_Talent_S_Xiao_04"],"talents":{"normalAttack":"Skill_A_03","elementalSkill":"Skill_S_Xiao_01","elementalBurst":"Skill_E_Xiao_01"},"costumes":[]},"name":null},"nameCard":"UI_NameCardPic_Xiao_P","patreon":{},"region":"ASIA"},"propMap":{"ascension":{"val":"6"},"level":{"val":"90"}},"proudSkillExtraLevelMap":{"2632":3},"stats":{"maxHp":{"value":20660.397207236576},"atk":{"value":2604.6521144384465},"def":{"value":850.216583292922},"elementalMastery":{"value":0},"energyRecharge":{"value":1.2202000166434508},"healingBonus":{"value":0},"critRate":{"value":0.7708000222409792},"critDamage":{"value":2.4285000124240943},"anemoDamageBonus":{"value":0.46600000715400003}},"talentsLevelMap":{"normalAttacks":{"icon":"https://enka.network/ui/Skill_A_03.png","level":10,"rawLevel":10,"id":10261,"boosted":false},"elementalSkill":{"icon":"https://enka.network/ui/Skill_S_Xiao_01.png","level":13,"rawLevel":10,"id":10262,"boosted":true},"elementalBurst":{"icon":"https://enka.network/ui/Skill_E_Xiao_01.png","level":10,"rawLevel":10,"id":10265,"boosted":false}},"weapon":{"weaponInfo":{"level":90,"promoteLevel":6,"refinementLevel":{"value":0}},"flat":{"icon":{"value":"UI_EquipIcon_Pole_Homa"}},"name":"Staff of Homa","icon":"https://enka.network/ui/UI_EquipIcon_Pole_Homa_Awaken.png"},"icon":"https://enka.network/ui/UI_AvatarIcon_Xiao.png","index":348,"nameCardLink":"https://enka.network/ui/UI_NameCardPic_Xiao_P.png","profilePictureLink":"https://enka.network/ui/UI_AvatarIcon_Xiao.png","characterMetadata":{"element":"Anemo"}},{"_id":"6530a972dbe6a10bf2194e12","calculation":{"id":"1000002601","result":675319.966692278,"additional":[{"name":"E Avg DMG","value":22321.01546871786,"quantity":1,"type":"E"},{"name":"E Avg DMG","value":24604.88471134403,"quantity":1,"type":"E"},{"name":"NA Avg DMG","value":4182.913022686904,"quantity":1,"type":"NA"},{"name":"Collision Plunge Avg DMG","value":14283.433881818035,"quantity":1,"type":"P"},{"name":"High Plunge Avg DMG","value":35675.03064374457,"quantity":1,"type":"P"},{"name":"NA Avg DMG","value":4495.226702245567,"quantity":1,"type":"NA"},{"name":"Collision Plunge Avg DMG","value":14797.473979553173,"quantity":1,"type":"P"},{"name":"High Plunge Avg DMG","value":36958.92332603283,"quantity":1,"type":"P"},{"name":"Collision Plunge Avg DMG","value":15311.51407728831,"quantity":1,"type":"P"},{"name":"High Plunge Avg DMG","value":40327.492900823156,"quantity":1,"type":"P"},{"name":"Collision Plunge Avg DMG","value":16146.16912934299,"quantity":1,"type":"P"},{"name":"High Plunge Avg DMG","value":40327.492900823156,"quantity":1,"type":"P"},{"name":"Collision Plunge Avg DMG","value":16146.16912934299,"quantity":1,"type":"P"},{"name":"High Plunge Avg DMG","value":40327.492900823156,"quantity":1,"type":"P"},{"name":"Collision Plunge Avg DMG","value":16146.16912934299,"quantity":1,"type":"P"},{"name":"High Plunge Avg DMG","value":41128.27711103694,"quantity":1,"type":"P"},{"name":"Collision Plunge Avg DMG","value":16466.784083662533,"quantity":1,"type":"P"},{"name":"High Plunge Avg DMG","value":41128.27711103694,"quantity":1,"type":"P"},{"name":"Collision Plunge Avg DMG","value":16466.784083662533,"quantity":1,"type":"P"},{"name":"High Plunge Avg DMG","value":41128.27711103694,"quantity":1,"type":"P"},{"name":"Collision Plunge Avg DMG","value":16787.399037982075,"quantity":1,"type":"P"},{"name":"High Plunge Avg DMG","value":41929.06132125073,"quantity":1,"type":"P"},{"name":"Collision Plunge Avg DMG","value":16787.399037982075,"quantity":1,"type":"P"},{"name":"High Plunge Avg DMG","value":41929.06132125073,"quantity":1,"type":"P"},{"name":"Collision Plunge Avg DMG","value":16787.399037982075,"quantity":1,"type":"P"},{"name":"High Plunge Avg DMG","value":42729.84553146451,"quantity":1,"type":"P"}]},"characterId":10000026,"type":"current","uid":"707358696","artifactObjects":{"EQUIP_SHOES":{"mainStatKey":"ATK%"},"EQUIP_RING":{"mainStatKey":"Anemo DMG Bonus"},"EQUIP_DRESS":{"mainStatKey":"Crit RATE"}},"artifactSets":{"Vermillion Hereafter":{"icon":"https://enka.network/ui/UI_RelicIcon_15023_4.png","count":4},"Viridescent Venerer":{"icon":"https://enka.network/ui/UI_RelicIcon_15002_4.png","count":1}},"constellation":1,"costumeId":"","critValue":236.3199973686071,"md5":"25d31fb9b28e38b2be1e170bffb5a469","name":"Xiao","owner":{"nickname":"Corvus","adventureRank":60.0000001712,"profilePicture":{"characterId":10000005,"id":"","assets":{"icon":"UI_AvatarIcon_PlayerBoy","sideIcon":"UI_AvatarIcon_Side_PlayerBoy","gachaIcon":"UI_Gacha_AvatarImg_PlayerBoy","constellations":["UI_Talent_S_PlayerWind_01","UI_Talent_S_PlayerWind_02","UI_Talent_U_PlayerWind_02","UI_Talent_S_PlayerWind_03","UI_Talent_U_PlayerWind_01","UI_Talent_S_PlayerWind_04"],"talents":{"normalAttack":"Skill_A_01","elementalSkill":"Skill_S_PlayerWind_01","elementalBurst":"Skill_E_PlayerWind_01"},"costumes":[]},"name":null},"nameCard":"UI_NameCardPic_Neuvillette_P","patreon":{},"region":"EU","enkaOwner":{}},"propMap":{"ascension":{"val":"6"},"level":{"val":"90"}},"proudSkillExtraLevelMap":{},"stats":{"maxHp":{"value":21359.275238255486},"atk":{"value":2487.6337022904554},"def":{"value":851.7304010146412},"elementalMastery":{"value":34.96999964095449},"energyRecharge":{"value":1.272000021565081},"healingBonus":{"value":0},"critRate":{"value":0.9030000198678259},"critDamage":{"value":2.2026999930934195},"anemoDamageBonus":{"value":0.466000004649}},"talentsLevelMap":{"normalAttacks":{"icon":"https://enka.network/ui/Skill_A_03.png","level":10,"rawLevel":10,"id":10261,"boosted":false},"elementalSkill":{"icon":"https://enka.network/ui/Skill_S_Xiao_01.png","level":10,"rawLevel":10,"id":10262,"boosted":false},"elementalBurst":{"icon":"https://enka.network/ui/Skill_E_Xiao_01.png","level":10,"rawLevel":10,"id":10265,"boosted":false}},"weapon":{"weaponInfo":{"level":90,"promoteLevel":6,"refinementLevel":{"value":0}},"flat":{"icon":{"value":"UI_EquipIcon_Pole_Homa"}},"name":"Staff of Homa","icon":"https://enka.network/ui/UI_EquipIcon_Pole_Homa_Awaken.png"},"lastBuildUpdate":1731118120575,"sortableType":"xiao","icon":"https://enka.network/ui/UI_AvatarIcon_Xiao.png","index":349,"nameCardLink":"https://enka.network/ui/UI_NameCardPic_Neuvillette_P.png","profilePictureLink":"https://enka.network/ui/UI_AvatarIcon_PlayerBoy.png","characterMetadata":{"element":"Anemo"}},{"_id":"6568e225dbe6a10bf230a4ac","calculation":{"id":"1000002601","result":675312.9594622832,"additional":[{"name":"E Avg DMG","value":22488.24389132154,"quantity":1,"type":"E"},{"name":"E Avg DMG","value":24789.223816068035,"quantity":1,"type":"E"},{"name":"NA Avg DMG","value":4207.152546159201,"quantity":1,"type":"NA"},{"name":"Collision Plunge Avg DMG","value":14337.867466658437,"quantity":1,"type":"P"},{"name":"High Plunge Avg DMG","value":35810.98673268634,"quantity":1,"type":"P"},{"name":"NA Avg DMG","value":4504.059215853605,"quantity":1,"type":"NA"},{"name":"Collision Plunge Avg DMG","value":14826.549018243366,"quantity":1,"type":"P"},{"name":"High Plunge Avg DMG","value":37031.54262086229,"quantity":1,"type":"P"},{"name":"Collision Plunge Avg DMG","value":15315.230569828296,"quantity":1,"type":"P"},{"name":"High Plunge Avg DMG","value":40272.343503773445,"quantity":1,"type":"P"},{"name":"Collision Plunge Avg DMG","value":16124.088622272147,"quantity":1,"type":"P"},{"name":"High Plunge Avg DMG","value":40272.343503773445,"quantity":1,"type":"P"},{"name":"Collision Plunge Avg DMG","value":16124.088622272147,"quantity":1,"type":"P"},{"name":"High Plunge Avg DMG","value":40272.343503773445,"quantity":1,"type":"P"},{"name":"Collision Plunge Avg DMG","value":16124.088622272147,"quantity":1,"type":"P"},{"name":"High Plunge Avg DMG","value":41072.032610332695,"quantity":1,"type":"P"},{"name":"Collision Plunge Avg DMG","value":16444.265123131074,"quantity":1,"type":"P"},{"name":"High Plunge Avg DMG","value":41072.032610332695,"quantity":1,"type":"P"},{"name":"Collision Plunge Avg DMG","value":16444.265123131074,"quantity":1,"type":"P"},{"name":"High Plunge Avg DMG","value":41072.032610332695,"quantity":1,"type":"P"},{"name":"Collision Plunge Avg DMG","value":16764.44162399,"quantity":1,"type":"P"},{"name":"High Plunge Avg DMG","value":41871.72171689193,"quantity":1,"type":"P"},{"name":"Collision Plunge Avg DMG","value":16764.44162399,"quantity":1,"type":"P"},{"name":"High Plunge Avg DMG","value":41871.72171689193,"quantity":1,"type":"P"},{"name":"Collision Plunge Avg DMG","value":16764.44162399,"quantity":1,"type":"P"},{"name":"High Plunge Avg DMG","value":42671.41082345117,"quantity":1,"type":"P"}]},"characterId":10000026,"type":"current","uid":"820939436","artifactObjects":{"EQUIP_SHOES":{"mainStatKey":"ATK%"},"EQUIP_RING":{"mainStatKey":"Anemo DMG Bonus"},"EQUIP_DRESS":{"mainStatKey":"Crit DMG"}},"artifactSets":{"Vermillion Hereafter":{"icon":"https://enka.network/ui/UI_RelicIcon_15023_4.png","count":4},"Gladiator's Finale":{"icon":"https://enka.network/ui/UI_RelicIcon_15001_4.png","count":1}},"constellation":1,"costumeId":"","critValue":233.99999785780494,"md5":"0c03317e62b9c854a6e5c19b91ca088a","name":"Xiao","owner":{"nickname":"허거덩","adventureRank":60.0000001554,"profilePicture":{"characterId":0,"id":7400,"assets":{"icon":"UI_AvatarIcon_Furina_Circle","oldIcon":"UI_AvatarIcon_Furina"},"name":null},"nameCard":"UI_NameCardPic_Sigewinne_P","patreon":{},"region":"ASIA","enkaOwner":{}},"propMap":{"ascension":{"val":"6"},"level":{"val":"90"}},"proudSkillExtraLevelMap":{},"stats":{"maxHp":{"value":20940.653454728406},"atk":{"value":2636.3257974997764},"def":{"value":859.4865460838578},"elementalMastery":{"value":0},"energyRecharge":{"value":1.2202000162294508},"healingBonus":{"value":0},"critRate":{"value":0.7281000147160577},"critDamage":{"value":2.5293000056889343},"anemoDamageBonus":{"value":0.466000006093}},"talentsLevelMap":{"normalAttacks":{"icon":"https://enka.network/ui/Skill_A_03.png","level":9,"rawLevel":9,"id":10261,"boosted":false},"elementalSkill":{"icon":"https://enka.network/ui/Skill_S_Xiao_01.png","level":9,"rawLevel":9,"id":10262,"boosted":false},"elementalBurst":{"icon":"https://enka.network/ui/Skill_E_Xiao_01.png","level":9,"rawLevel":9,"id":10265,"boosted":false}},"weapon":{"weaponInfo":{"level":90,"promoteLevel":6,"refinementLevel":{"value":1}},"flat":{"icon":{"value":"UI_EquipIcon_Pole_Morax"}},"name":"Primordial Jade Winged-Spear","icon":"https://enka.network/ui/UI_EquipIcon_Pole_Morax_Awaken.png"},"lastBuildUpdate":1727303654533,"sortableType":"xiao","icon":"https://enka.network/ui/UI_AvatarIcon_Xiao.png","index":350,"nameCardLink":"https://enka.network/ui/UI_NameCardPic_Sigewinne_P.png","profilePictureLink":"https://enka.network/ui/UI_AvatarIcon_Furina.png","characterMetadata":{"element":"Anemo"}},{"_id":"64ea59abdbe6a10bf2adee9c","calculation":{"id":"1000002601","result":675248.1223637586,"additional":[{"name":"E Avg DMG","value":22278.997811120826,"quantity":1,"type":"E"},{"name":"E Avg DMG","value":24558.567832260076,"quantity":1,"type":"E"},{"name":"NA Avg DMG","value":4176.719489097835,"quantity":1,"type":"NA"},{"name":"Collision Plunge Avg DMG","value":14268.9931041217,"quantity":1,"type":"P"},{"name":"High Plunge Avg DMG","value":35638.96262319021,"quantity":1,"type":"P"},{"name":"NA Avg DMG","value":4492.646499237232,"quantity":1,"type":"NA"},{"name":"Collision Plunge Avg DMG","value":14788.980417513523,"quantity":1,"type":"P"},{"name":"High Plunge Avg DMG","value":36937.709373663536,"quantity":1,"type":"P"},{"name":"Collision Plunge Avg DMG","value":15308.967730905351,"quantity":1,"type":"P"},{"name":"High Plunge Avg DMG","value":40336.159169774306,"quantity":1,"type":"P"},{"name":"Collision Plunge Avg DMG","value":16149.638897338482,"quantity":1,"type":"P"},{"name":"High Plunge Avg DMG","value":40336.159169774306,"quantity":1,"type":"P"},{"name":"Collision Plunge Avg DMG","value":16149.638897338482,"quantity":1,"type":"P"},{"name":"High Plunge Avg DMG","value":40336.159169774306,"quantity":1,"type":"P"},{"name":"Collision Plunge Avg DMG","value":16149.638897338482,"quantity":1,"type":"P"},{"name":"High Plunge Avg DMG","value":41137.11546493843,"quantity":1,"type":"P"},{"name":"Collision Plunge Avg DMG","value":16470.322750379786,"quantity":1,"type":"P"},{"name":"High Plunge Avg DMG","value":41137.11546493843,"quantity":1,"type":"P"},{"name":"Collision Plunge Avg DMG","value":16470.322750379786,"quantity":1,"type":"P"},{"name":"High Plunge Avg DMG","value":41137.11546493843,"quantity":1,"type":"P"},{"name":"Collision Plunge Avg DMG","value":16791.006603421087,"quantity":1,"type":"P"},{"name":"High Plunge Avg DMG","value":41938.071760102546,"quantity":1,"type":"P"},{"name":"Collision Plunge Avg DMG","value":16791.006603421087,"quantity":1,"type":"P"},{"name":"High Plunge Avg DMG","value":41938.071760102546,"quantity":1,"type":"P"},{"name":"Collision Plunge Avg DMG","value":16791.006603421087,"quantity":1,"type":"P"},{"name":"High Plunge Avg DMG","value":42739.02805526666,"quantity":1,"type":"P"}]},"characterId":10000026,"type":"current","uid":"821939243","artifactObjects":{"EQUIP_SHOES":{"mainStatKey":"ATK%"},"EQUIP_RING":{"mainStatKey":"Anemo DMG Bonus"},"EQUIP_DRESS":{"mainStatKey":"Crit DMG"}},"artifactSets":{"Vermillion Hereafter":{"icon":"https://enka.network/ui/UI_RelicIcon_15023_4.png","count":4},"Scroll of the Hero of Cinder City":{"icon":"https://enka.network/ui/UI_RelicIcon_15037_4.png","count":1}},"constellation":6,"costumeId":"","critValue":262.7499967297585,"md5":"3f4cf2552b31ac00732c03264e986e82","name":"Xiao","owner":{"nickname":"いずいず","adventureRank":60.0000000692,"profilePicture":{"characterId":10000052,"id":"","assets":{"icon":"UI_AvatarIcon_Shougun","sideIcon":"UI_AvatarIcon_Side_Shougun","gachaIcon":"UI_Gacha_AvatarImg_Shougun","constellations":["UI_Talent_S_Shougun_01","UI_Talent_S_Shougun_03","UI_Talent_U_Shougun_02","UI_Talent_S_Shougun_02","UI_Talent_U_Shougun_01","UI_Talent_S_Shougun_04"],"talents":{"normalAttack":"Skill_A_03","elementalSkill":"Skill_S_Shougun_01","elementalBurst":"Skill_E_Shougun_01"},"costumes":[]},"name":null},"nameCard":"UI_NameCardPic_Yae1_P","patreon":{},"region":"ASIA","enkaOwner":{}},"propMap":{"ascension":{"val":"6"},"level":{"val":"90"}},"proudSkillExtraLevelMap":{"2632":3,"2639":3},"stats":{"maxHp":{"value":22827.395555403193},"atk":{"value":2454.552826948912},"def":{"value":799.2965448000001},"elementalMastery":{"value":0},"energyRecharge":{"value":1.2072000275752302},"healingBonus":{"value":0},"critRate":{"value":0.7086000307813713},"critDamage":{"value":2.8558000114128426},"anemoDamageBonus":{"value":0.46600000907100003}},"talentsLevelMap":{"normalAttacks":{"icon":"https://enka.network/ui/Skill_A_03.png","level":10,"rawLevel":10,"id":10261,"boosted":false},"elementalSkill":{"icon":"https://enka.network/ui/Skill_S_Xiao_01.png","level":13,"rawLevel":10,"id":10262,"boosted":true},"elementalBurst":{"icon":"https://enka.network/ui/Skill_E_Xiao_01.png","level":13,"rawLevel":10,"id":10265,"boosted":true}},"weapon":{"weaponInfo":{"level":90,"promoteLevel":6,"refinementLevel":{"value":4}},"flat":{"icon":{"value":"UI_EquipIcon_Pole_Morax"}},"name":"Primordial Jade Winged-Spear","icon":"https://enka.network/ui/UI_EquipIcon_Pole_Morax_Awaken.png"},"lastBuildUpdate":1731052124260,"sortableType":"xiao","icon":"https://enka.network/ui/UI_AvatarIcon_Xiao.png","index":351,"nameCardLink":"https://enka.network/ui/UI_NameCardPic_Yae1_P.png","profilePictureLink":"https://enka.network/ui/UI_AvatarIcon_Shougun.png","characterMetadata":{"element":"Anemo"}},{"_id":"657ad1b9dbe6a10bf21e5bd1","calculation":{"id":"1000002601","result":675189.6895774688,"additional":[{"name":"E Avg DMG","value":22295.02550106986,"quantity":1,"type":"E"},{"name":"E Avg DMG","value":24576.23547689248,"quantity":1,"type":"E"},{"name":"NA Avg DMG","value":4178.961757919696,"quantity":1,"type":"NA"},{"name":"Collision Plunge Avg DMG","value":14273.610788487702,"quantity":1,"type":"P"},{"name":"High Plunge Avg DMG","value":35650.49598642928,"quantity":1,"type":"P"},{"name":"NA Avg DMG","value":4493.209781970087,"quantity":1,"type":"NA"},{"name":"Collision Plunge Avg DMG","value":14790.834642480286,"quantity":1,"type":"P"},{"name":"High Plunge Avg DMG","value":36942.340580210715,"quantity":1,"type":"P"},{"name":"Collision Plunge Avg DMG","value":15308.058496472877,"quantity":1,"type":"P"},{"name":"High Plunge Avg DMG","value":40326.80022489533,"quantity":1,"type":"P"},{"name":"Collision Plunge Avg DMG","value":16145.891798374012,"quantity":1,"type":"P"},{"name":"High Plunge Avg DMG","value":40326.80022489533,"quantity":1,"type":"P"},{"name":"Collision Plunge Avg DMG","value":16145.891798374012,"quantity":1,"type":"P"},{"name":"High Plunge Avg DMG","value":40326.80022489533,"quantity":1,"type":"P"},{"name":"Collision Plunge Avg DMG","value":16145.891798374012,"quantity":1,"type":"P"},{"name":"High Plunge Avg DMG","value":41127.57068201707,"quantity":1,"type":"P"},{"name":"Collision Plunge Avg DMG","value":16466.501246282565,"quantity":1,"type":"P"},{"name":"High Plunge Avg DMG","value":41127.57068201707,"quantity":1,"type":"P"},{"name":"Collision Plunge Avg DMG","value":16466.501246282565,"quantity":1,"type":"P"},{"name":"High Plunge Avg DMG","value":41127.57068201707,"quantity":1,"type":"P"},{"name":"Collision Plunge Avg DMG","value":16787.110694191117,"quantity":1,"type":"P"},{"name":"High Plunge Avg DMG","value":41928.341139138814,"quantity":1,"type":"P"},{"name":"Collision Plunge Avg DMG","value":16787.110694191117,"quantity":1,"type":"P"},{"name":"High Plunge Avg DMG","value":41928.341139138814,"quantity":1,"type":"P"},{"name":"Collision Plunge Avg DMG","value":16787.110694191117,"quantity":1,"type":"P"},{"name":"High Plunge Avg DMG","value":42729.11159626057,"quantity":1,"type":"P"}]},"characterId":10000026,"type":"current","uid":"801502315","artifactObjects":{"EQUIP_SHOES":{"mainStatKey":"ATK%"},"EQUIP_RING":{"mainStatKey":"Anemo DMG Bonus"},"EQUIP_DRESS":{"mainStatKey":"Crit RATE"}},"artifactSets":{"Vermillion Hereafter":{"icon":"https://enka.network/ui/UI_RelicIcon_15023_4.png","count":4},"Obsidian Codex":{"icon":"https://enka.network/ui/UI_RelicIcon_15038_4.png","count":1}},"constellation":1,"costumeId":"","critValue":241.7499970286515,"md5":"4a13776189c612fb9c71cc5b00028dd8","name":"Xiao","owner":{"nickname":"Xiao_Impact","adventureRank":60.0000002989,"profilePicture":{"characterId":0,"id":2800,"assets":{"icon":"UI_AvatarIcon_Xiao_Circle","oldIcon":"UI_AvatarIcon_Xiao"},"name":null},"nameCard":"UI_NameCardPic_Xiao_P","patreon":{},"region":"ASIA","enkaOwner":{}},"propMap":{"ascension":{"val":"6"},"level":{"val":"90"}},"proudSkillExtraLevelMap":{},"stats":{"maxHp":{"value":21078.656674030728},"atk":{"value":2469.442447259705},"def":{"value":911.0145344223969},"elementalMastery":{"value":0},"energyRecharge":{"value":1.2850000233745922},"healingBonus":{"value":0},"critRate":{"value":0.848500017771483},"critDamage":{"value":2.3659999916795496},"anemoDamageBonus":{"value":0.466000000265}},"talentsLevelMap":{"normalAttacks":{"icon":"https://enka.network/ui/Skill_A_03.png","level":10,"rawLevel":10,"id":10261,"boosted":false},"elementalSkill":{"icon":"https://enka.network/ui/Skill_S_Xiao_01.png","level":10,"rawLevel":10,"id":10262,"boosted":false},"elementalBurst":{"icon":"https://enka.network/ui/Skill_E_Xiao_01.png","level":10,"rawLevel":10,"id":10265,"boosted":false}},"weapon":{"weaponInfo":{"level":90,"promoteLevel":6,"refinementLevel":{"value":0}},"flat":{"icon":{"value":"UI_EquipIcon_Pole_Homa"}},"name":"Staff of Homa","icon":"https://enka.network/ui/UI_EquipIcon_Pole_Homa_Awaken.png"},"lastBuildUpdate":1727443467763,"sortableType":"xiao","icon":"https://enka.network/ui/UI_AvatarIcon_Xiao.png","index":352,"nameCardLink":"https://enka.network/ui/UI_NameCardPic_Xiao_P.png","profilePictureLink":"https://enka.network/ui/UI_AvatarIcon_Xiao.png","characterMetadata":{"element":"Anemo"}},{"_id":"64ea5930dbe6a10bf2ab6a2a","calculation":{"id":"1000002601","result":675184.9405611843},"characterId":10000026,"type":"current","uid":"823878622","artifactObjects":{"EQUIP_SHOES":{"mainStatKey":"ATK%"},"EQUIP_RING":{"mainStatKey":"Anemo DMG Bonus"},"EQUIP_DRESS":{"mainStatKey":"Crit RATE"}},"artifactSets":{"Vermillion Hereafter":{"icon":"https://enka.network/ui/UI_RelicIcon_15023_4.png","count":4},"Crimson Witch of Flames":{"icon":"https://enka.network/ui/UI_RelicIcon_15006_4.png","count":1}},"constellation":0,"costumeId":"","critValue":232.41999759034084,"md5":"d1919bdb45d0c00925c22470f2dfd970","name":"Xiao","owner":{"nickname":"Nguỵt","adventureRank":59,"profilePicture":10000078,"nameCard":"UI_NameCardPic_Cyno_P","patreon":{},"region":"ASIA"},"propMap":{"ascension":{"val":"6"},"level":{"val":"90"}},"proudSkillExtraLevelMap":{},"stats":{"maxHp":{"value":20062.897206698777},"atk":{"value":2528.837843262753},"def":{"value":935.3594268686445},"elementalMastery":{"value":23.309999465942383},"energyRecharge":{"value":1.2980000004172325},"healingBonus":{"value":0},"critRate":{"value":0.8834999997764825},"critDamage":{"value":2.2026999709904196},"anemoDamageBonus":{"value":0.466}},"talentsLevelMap":{"normalAttacks":{"icon":"https://enka.network/ui/Skill_A_03.png","level":10,"rawLevel":10,"id":10261,"boosted":false},"elementalSkill":{"icon":"https://enka.network/ui/Skill_S_Xiao_01.png","level":10,"rawLevel":10,"id":10262,"boosted":false},"elementalBurst":{"icon":"https://enka.network/ui/Skill_E_Xiao_01.png","level":10,"rawLevel":10,"id":10265,"boosted":false}},"weapon":{"weaponInfo":{"level":90,"promoteLevel":6,"refinementLevel":{"value":0}},"flat":{"icon":{"value":"UI_EquipIcon_Pole_Morax"}},"name":"Primordial Jade Winged-Spear","icon":"https://enka.network/ui/UI_EquipIcon_Pole_Morax_Awaken.png"},"icon":"https://enka.network/ui/UI_AvatarIcon_Xiao.png","index":353,"nameCardLink":"https://enka.network/ui/UI_NameCardPic_Cyno_P.png","profilePictureLink":"https://enka.network/ui/UI_AvatarIcon_Alhatham.png","characterMetadata":{"element":"Anemo"}},{"_id":"64ea58dedbe6a10bf2a9b9c1","calculation":{"id":"1000002601","result":675052.7019972086,"additional":[{"name":"E Avg DMG","value":22400.620693942532,"quantity":1,"type":"E"},{"name":"E Avg DMG","value":24692.635088430692,"quantity":1,"type":"E"},{"name":"NA Avg DMG","value":4194.08189600724,"quantity":1,"type":"NA"},{"name":"Collision Plunge Avg DMG","value":14306.606814838997,"quantity":1,"type":"P"},{"name":"High Plunge Avg DMG","value":35732.90853938706,"quantity":1,"type":"P"},{"name":"NA Avg DMG","value":4498.136932889746,"quantity":1,"type":"NA"},{"name":"Collision Plunge Avg DMG","value":14807.053932931327,"quantity":1,"type":"P"},{"name":"High Plunge Avg DMG","value":36982.85070464215,"quantity":1,"type":"P"},{"name":"Collision Plunge Avg DMG","value":15307.501051023657,"quantity":1,"type":"P"},{"name":"High Plunge Avg DMG","value":40282.62837029791,"quantity":1,"type":"P"},{"name":"Collision Plunge Avg DMG","value":16128.206438244122,"quantity":1,"type":"P"},{"name":"High Plunge Avg DMG","value":40282.62837029791,"quantity":1,"type":"P"},{"name":"Collision Plunge Avg DMG","value":16128.206438244122,"quantity":1,"type":"P"},{"name":"High Plunge Avg DMG","value":40282.62837029791,"quantity":1,"type":"P"},{"name":"Collision Plunge Avg DMG","value":16128.206438244122,"quantity":1,"type":"P"},{"name":"High Plunge Avg DMG","value":41082.52170544349,"quantity":1,"type":"P"},{"name":"Collision Plunge Avg DMG","value":16448.464707372255,"quantity":1,"type":"P"},{"name":"High Plunge Avg DMG","value":41082.52170544349,"quantity":1,"type":"P"},{"name":"Collision Plunge Avg DMG","value":16448.464707372255,"quantity":1,"type":"P"},{"name":"High Plunge Avg DMG","value":41082.52170544349,"quantity":1,"type":"P"},{"name":"Collision Plunge Avg DMG","value":16768.722976500394,"quantity":1,"type":"P"},{"name":"High Plunge Avg DMG","value":41882.41504058908,"quantity":1,"type":"P"},{"name":"Collision Plunge Avg DMG","value":16768.722976500394,"quantity":1,"type":"P"},{"name":"High Plunge Avg DMG","value":41882.41504058908,"quantity":1,"type":"P"},{"name":"Collision Plunge Avg DMG","value":16768.722976500394,"quantity":1,"type":"P"},{"name":"High Plunge Avg DMG","value":42682.30837573466,"quantity":1,"type":"P"}]},"characterId":10000026,"type":"current","uid":"722541209","artifactObjects":{"EQUIP_SHOES":{"mainStatKey":"ATK%"},"EQUIP_RING":{"mainStatKey":"Anemo DMG Bonus"},"EQUIP_DRESS":{"mainStatKey":"Crit RATE"}},"artifactSets":{"Vermillion Hereafter":{"icon":"https://enka.network/ui/UI_RelicIcon_15023_4.png","count":4},"Unfinished Reverie":{"icon":"https://enka.network/ui/UI_RelicIcon_15036_4.png","count":1}},"constellation":0,"costumeId":"","critValue":231.639997725394,"md5":"e01be002f7fe5e93de137325f30b885b","name":"Xiao","owner":{"nickname":"Мася","adventureRank":60.0000002335,"profilePicture":{"characterId":0,"id":3900,"assets":{"icon":"UI_AvatarIcon_Shougun_Circle","oldIcon":"UI_AvatarIcon_Shougun"},"name":null},"nameCard":"UI_NameCardPic_WishingPond_P","patreon":{},"region":"EU","enkaOwner":{}},"propMap":{"ascension":{"val":"6"},"level":{"val":"90"}},"proudSkillExtraLevelMap":{},"stats":{"maxHp":{"value":22115.514796879306},"atk":{"value":2564.3148130910226},"def":{"value":799.2965448000001},"elementalMastery":{"value":20.980000373736328},"energyRecharge":{"value":1.20720001902923},"healingBonus":{"value":0},"critRate":{"value":0.8291000296039235},"critDamage":{"value":2.3037000056070935},"anemoDamageBonus":{"value":0.466000000773}},"talentsLevelMap":{"normalAttacks":{"icon":"https://enka.network/ui/Skill_A_03.png","level":10,"rawLevel":10,"id":10261,"boosted":false},"elementalSkill":{"icon":"https://enka.network/ui/Skill_S_Xiao_01.png","level":10,"rawLevel":10,"id":10262,"boosted":false},"elementalBurst":{"icon":"https://enka.network/ui/Skill_E_Xiao_01.png","level":10,"rawLevel":10,"id":10265,"boosted":false}},"weapon":{"weaponInfo":{"level":80,"promoteLevel":5,"refinementLevel":{"value":0}},"flat":{"icon":{"value":"UI_EquipIcon_Pole_Shanty"}},"name":"Ballad of the Fjords","icon":"https://enka.network/ui/UI_EquipIcon_Pole_Shanty_Awaken.png"},"lastBuildUpdate":1729345441534,"sortableType":"xiao","icon":"https://enka.network/ui/UI_AvatarIcon_Xiao.png","index":354,"nameCardLink":"https://enka.network/ui/UI_NameCardPic_WishingPond_P.png","profilePictureLink":"https://enka.network/ui/UI_AvatarIcon_Shougun.png","characterMetadata":{"element":"Anemo"}},{"_id":"65abf09ddbe6a10bf275945f","calculation":{"id":"1000002601","result":675045.636144073,"additional":[{"name":"E Avg DMG","value":22494.844741700093,"quantity":1,"type":"E"},{"name":"E Avg DMG","value":24796.500058546382,"quantity":1,"type":"E"},{"name":"NA Avg DMG","value":4207.735165171507,"quantity":1,"type":"NA"},{"name":"Collision Plunge Avg DMG","value":14337.244790247993,"quantity":1,"type":"P"},{"name":"High Plunge Avg DMG","value":35809.43150442628,"quantity":1,"type":"P"},{"name":"NA Avg DMG","value":4503.098279348601,"quantity":1,"type":"NA"},{"name":"Collision Plunge Avg DMG","value":14823.385788917982,"quantity":1,"type":"P"},{"name":"High Plunge Avg DMG","value":37023.641978478256,"quantity":1,"type":"P"},{"name":"Collision Plunge Avg DMG","value":15309.526787587973,"quantity":1,"type":"P"},{"name":"High Plunge Avg DMG","value":40251.334863579636,"quantity":1,"type":"P"},{"name":"Collision Plunge Avg DMG","value":16115.67726234504,"quantity":1,"type":"P"},{"name":"High Plunge Avg DMG","value":40251.334863579636,"quantity":1,"type":"P"},{"name":"Collision Plunge Avg DMG","value":16115.67726234504,"quantity":1,"type":"P"},{"name":"High Plunge Avg DMG","value":40251.334863579636,"quantity":1,"type":"P"},{"name":"Collision Plunge Avg DMG","value":16115.67726234504,"quantity":1,"type":"P"},{"name":"High Plunge Avg DMG","value":41050.60680057706,"quantity":1,"type":"P"},{"name":"Collision Plunge Avg DMG","value":16435.68673843212,"quantity":1,"type":"P"},{"name":"High Plunge Avg DMG","value":41050.60680057706,"quantity":1,"type":"P"},{"name":"Collision Plunge Avg DMG","value":16435.68673843212,"quantity":1,"type":"P"},{"name":"High Plunge Avg DMG","value":41050.60680057706,"quantity":1,"type":"P"},{"name":"Collision Plunge Avg DMG","value":16755.696214519197,"quantity":1,"type":"P"},{"name":"High Plunge Avg DMG","value":41849.878737574465,"quantity":1,"type":"P"},{"name":"Collision Plunge Avg DMG","value":16755.696214519197,"quantity":1,"type":"P"},{"name":"High Plunge Avg DMG","value":41849.878737574465,"quantity":1,"type":"P"},{"name":"Collision Plunge Avg DMG","value":16755.696214519197,"quantity":1,"type":"P"},{"name":"High Plunge Avg DMG","value":42649.15067457187,"quantity":1,"type":"P"}]},"characterId":10000026,"type":"current","uid":"833004105","artifactObjects":{"EQUIP_SHOES":{"mainStatKey":"ATK%"},"EQUIP_RING":{"mainStatKey":"Anemo DMG Bonus"},"EQUIP_DRESS":{"mainStatKey":"Crit DMG"}},"artifactSets":{"Vermillion Hereafter":{"icon":"https://enka.network/ui/UI_RelicIcon_15023_4.png","count":4},"Echoes of an Offering":{"icon":"https://enka.network/ui/UI_RelicIcon_15024_4.png","count":1}},"constellation":4,"costumeId":"","critValue":221.59999751916072,"md5":"92f60a1feb790c91549262f9cc8d7bc5","name":"Xiao","owner":{"nickname":"ĄɮáŋMʉối","adventureRank":60.0000004946,"profilePicture":{"characterId":10000026,"id":"","assets":{"icon":"UI_AvatarIcon_Xiao","sideIcon":"UI_AvatarIcon_Side_Xiao","gachaIcon":"UI_Gacha_AvatarImg_Xiao","constellations":["UI_Talent_S_Xiao_01","UI_Talent_S_Xiao_02","UI_Talent_U_Xiao_01","UI_Talent_S_Xiao_03","UI_Talent_U_Xiao_02","UI_Talent_S_Xiao_04"],"talents":{"normalAttack":"Skill_A_03","elementalSkill":"Skill_S_Xiao_01","elementalBurst":"Skill_E_Xiao_01"},"costumes":[]},"name":null},"nameCard":"UI_NameCardPic_Neuvillette_P","patreon":{},"region":"ASIA","enkaOwner":{}},"propMap":{"ascension":{"val":"6"},"level":{"val":"90"}},"proudSkillExtraLevelMap":{"2632":3},"stats":{"maxHp":{"value":21918.495152843054},"atk":{"value":2650.8809972652107},"def":{"value":820.1265454518061},"elementalMastery":{"value":0},"energyRecharge":{"value":1.3108000154739097},"healingBonus":{"value":0},"critRate":{"value":0.8292000213725682},"critDamage":{"value":2.203100008226471},"anemoDamageBonus":{"value":0.466000007281}},"talentsLevelMap":{"normalAttacks":{"icon":"https://enka.network/ui/Skill_A_03.png","level":10,"rawLevel":10,"id":10261,"boosted":false},"elementalSkill":{"icon":"https://enka.network/ui/Skill_S_Xiao_01.png","level":13,"rawLevel":10,"id":10262,"boosted":true},"elementalBurst":{"icon":"https://enka.network/ui/Skill_E_Xiao_01.png","level":10,"rawLevel":10,"id":10265,"boosted":false}},"weapon":{"weaponInfo":{"level":90,"promoteLevel":6,"refinementLevel":{"value":0}},"flat":{"icon":{"value":"UI_EquipIcon_Pole_Homa"}},"name":"Staff of Homa","icon":"https://enka.network/ui/UI_EquipIcon_Pole_Homa_Awaken.png"},"lastBuildUpdate":1725368013650,"sortableType":"xiao","icon":"https://enka.network/ui/UI_AvatarIcon_Xiao.png","index":355,"nameCardLink":"https://enka.network/ui/UI_NameCardPic_Neuvillette_P.png","profilePictureLink":"https://enka.network/ui/UI_AvatarIcon_Xiao.png","characterMetadata":{"element":"Anemo"}},{"_id":"668421438f1b3f627f2b35f2","calculation":{"id":"1000002601","result":674993.1757291023,"additional":[{"name":"E Avg DMG","value":22111.395468289084,"quantity":1,"type":"E"},{"name":"E Avg DMG","value":24373.81654978895,"quantity":1,"type":"E"},{"name":"NA Avg DMG","value":4152.058717261048,"quantity":1,"type":"NA"},{"name":"Collision Plunge Avg DMG","value":14211.719217679532,"quantity":1,"type":"P"},{"name":"High Plunge Avg DMG","value":35495.912452564815,"quantity":1,"type":"P"},{"name":"NA Avg DMG","value":4482.509561136236,"quantity":1,"type":"NA"},{"name":"Collision Plunge Avg DMG","value":14755.611449112688,"quantity":1,"type":"P"},{"name":"High Plunge Avg DMG","value":36854.36534168217,"quantity":1,"type":"P"},{"name":"Collision Plunge Avg DMG","value":15299.503680545844,"quantity":1,"type":"P"},{"name":"High Plunge Avg DMG","value":40372.95813400279,"quantity":1,"type":"P"},{"name":"Collision Plunge Avg DMG","value":16164.372327499364,"quantity":1,"type":"P"},{"name":"High Plunge Avg DMG","value":40372.95813400279,"quantity":1,"type":"P"},{"name":"Collision Plunge Avg DMG","value":16164.372327499364,"quantity":1,"type":"P"},{"name":"High Plunge Avg DMG","value":40372.95813400279,"quantity":1,"type":"P"},{"name":"Collision Plunge Avg DMG","value":16164.372327499364,"quantity":1,"type":"P"},{"name":"High Plunge Avg DMG","value":41174.6451480887,"quantity":1,"type":"P"},{"name":"Collision Plunge Avg DMG","value":16485.348743019727,"quantity":1,"type":"P"},{"name":"High Plunge Avg DMG","value":41174.6451480887,"quantity":1,"type":"P"},{"name":"Collision Plunge Avg DMG","value":16485.348743019727,"quantity":1,"type":"P"},{"name":"High Plunge Avg DMG","value":41174.6451480887,"quantity":1,"type":"P"},{"name":"Collision Plunge Avg DMG","value":16806.32515854009,"quantity":1,"type":"P"},{"name":"High Plunge Avg DMG","value":41976.33216217462,"quantity":1,"type":"P"},{"name":"Collision Plunge Avg DMG","value":16806.32515854009,"quantity":1,"type":"P"},{"name":"High Plunge Avg DMG","value":41976.33216217462,"quantity":1,"type":"P"},{"name":"Collision Plunge Avg DMG","value":16806.32515854009,"quantity":1,"type":"P"},{"name":"High Plunge Avg DMG","value":42778.01917626054,"quantity":1,"type":"P"}]},"characterId":10000026,"type":"current","uid":"747492547","artifactObjects":{"EQUIP_SHOES":{"mainStatKey":"ATK%"},"EQUIP_RING":{"mainStatKey":"Anemo DMG Bonus"},"EQUIP_DRESS":{"mainStatKey":"Crit DMG"}},"artifactSets":{"Vermillion Hereafter":{"icon":"https://enka.network/ui/UI_RelicIcon_15023_4.png","count":4},"Shimenawa's Reminiscence":{"icon":"https://enka.network/ui/UI_RelicIcon_15019_4.png","count":1}},"constellation":6,"costumeId":"","critValue":258.88999832503004,"lastBuildUpdate":1719935299353,"md5":"4e587e4b0292872afb655d1d352359fb","name":"Xiao","owner":{"nickname":"青鸢.云行","adventureRank":60.0000008684,"profilePicture":{"characterId":0,"id":6800,"assets":{"icon":"UI_AvatarIcon_Linette_Circle","oldIcon":"UI_AvatarIcon_Linette"},"name":null},"nameCard":"UI_NameCardPic_Liney_P","patreon":{},"region":"EU","enkaOwner":{}},"propMap":{"ascension":{"val":"6"},"level":{"val":"90"}},"proudSkillExtraLevelMap":{"2632":3,"2639":3},"sortableType":"xiao","stats":{"maxHp":{"value":20809.776669177616},"atk":{"value":2329.017636333832},"def":{"value":882.9255376923468},"elementalMastery":{"value":32.64000047984844},"energyRecharge":{"value":1.2267000131542065},"healingBonus":{"value":0},"critRate":{"value":0.8603000176947007},"critDamage":{"value":2.513800009975899},"anemoDamageBonus":{"value":0.46600000652600004}},"talentsLevelMap":{"normalAttacks":{"icon":"https://enka.network/ui/Skill_A_03.png","level":10,"rawLevel":10,"id":10261,"boosted":false},"elementalSkill":{"icon":"https://enka.network/ui/Skill_S_Xiao_01.png","level":13,"rawLevel":10,"id":10262,"boosted":true},"elementalBurst":{"icon":"https://enka.network/ui/Skill_E_Xiao_01.png","level":13,"rawLevel":10,"id":10265,"boosted":true}},"weapon":{"weaponInfo":{"level":90,"promoteLevel":6,"refinementLevel":{"value":0}},"flat":{"icon":{"value":"UI_EquipIcon_Pole_Homa"}},"name":"Staff of Homa","icon":"https://enka.network/ui/UI_EquipIcon_Pole_Homa_Awaken.png"},"icon":"https://enka.network/ui/UI_AvatarIcon_Xiao.png","index":356,"nameCardLink":"https://enka.network/ui/UI_NameCardPic_Liney_P.png","profilePictureLink":"https://enka.network/ui/UI_AvatarIcon_Linette.png","characterMetadata":{"element":"Anemo"}},{"_id":"667a2f5a8f1b3f627fb4da62","calculation":{"id":"1000002601","result":674914.7670800118,"additional":[{"name":"E Avg DMG","value":22260.769868843796,"quantity":1,"type":"E"},{"name":"E Avg DMG","value":24538.474824224173,"quantity":1,"type":"E"},{"name":"NA Avg DMG","value":4173.609236291711,"quantity":1,"type":"NA"},{"name":"Collision Plunge Avg DMG","value":14259.592509397964,"quantity":1,"type":"P"},{"name":"High Plunge Avg DMG","value":35615.483219874906,"quantity":1,"type":"P"},{"name":"NA Avg DMG","value":4490.045263112542,"quantity":1,"type":"NA"},{"name":"Collision Plunge Avg DMG","value":14780.417618255691,"quantity":1,"type":"P"},{"name":"High Plunge Avg DMG","value":36916.32249089802,"quantity":1,"type":"P"},{"name":"Collision Plunge Avg DMG","value":15301.242727113422,"quantity":1,"type":"P"},{"name":"High Plunge Avg DMG","value":40318.60883120804,"quantity":1,"type":"P"},{"name":"Collision Plunge Avg DMG","value":16142.612159141165,"quantity":1,"type":"P"},{"name":"High Plunge Avg DMG","value":40318.60883120804,"quantity":1,"type":"P"},{"name":"Collision Plunge Avg DMG","value":16142.612159141165,"quantity":1,"type":"P"},{"name":"High Plunge Avg DMG","value":40318.60883120804,"quantity":1,"type":"P"},{"name":"Collision Plunge Avg DMG","value":16142.612159141165,"quantity":1,"type":"P"},{"name":"High Plunge Avg DMG","value":41119.21662947182,"quantity":1,"type":"P"},{"name":"Collision Plunge Avg DMG","value":16463.156482311177,"quantity":1,"type":"P"},{"name":"High Plunge Avg DMG","value":41119.21662947182,"quantity":1,"type":"P"},{"name":"Collision Plunge Avg DMG","value":16463.156482311177,"quantity":1,"type":"P"},{"name":"High Plunge Avg DMG","value":41119.21662947182,"quantity":1,"type":"P"},{"name":"Collision Plunge Avg DMG","value":16783.700805481192,"quantity":1,"type":"P"},{"name":"High Plunge Avg DMG","value":41919.824427735606,"quantity":1,"type":"P"},{"name":"Collision Plunge Avg DMG","value":16783.700805481192,"quantity":1,"type":"P"},{"name":"High Plunge Avg DMG","value":41919.824427735606,"quantity":1,"type":"P"},{"name":"Collision Plunge Avg DMG","value":16783.700805481192,"quantity":1,"type":"P"},{"name":"High Plunge Avg DMG","value":42720.43222599938,"quantity":1,"type":"P"}]},"characterId":10000026,"type":"current","uid":"880186298","artifactObjects":{"EQUIP_SHOES":{"mainStatKey":"ATK%"},"EQUIP_RING":{"mainStatKey":"Anemo DMG Bonus"},"EQUIP_DRESS":{"mainStatKey":"Crit RATE"}},"artifactSets":{"Vermillion Hereafter":{"icon":"https://enka.network/ui/UI_RelicIcon_15023_4.png","count":4},"Crimson Witch of Flames":{"icon":"https://enka.network/ui/UI_RelicIcon_15006_4.png","count":1}},"constellation":0,"costumeId":"","critValue":239.42999723774938,"lastBuildUpdate":1730826878536,"md5":"93a06f1f7ded549bd781d513b7949997","name":"Xiao","owner":{"nickname":"S!dhu","adventureRank":59.0000004245,"profilePicture":{"characterId":0,"id":2800,"assets":{"icon":"UI_AvatarIcon_Xiao_Circle","oldIcon":"UI_AvatarIcon_Xiao"},"name":null},"nameCard":"UI_NameCardPic_Xiao_P","patreon":{},"region":"ASIA","enkaOwner":{}},"propMap":{"ascension":{"val":"6"},"level":{"val":"90"}},"proudSkillExtraLevelMap":{},"sortableType":"xiao","stats":{"maxHp":{"value":20361.646663506002},"atk":{"value":2448.5994488111637},"def":{"value":799.2965448000001},"elementalMastery":{"value":34.969999948454486},"energyRecharge":{"value":1.4534000155504132},"healingBonus":{"value":0},"critRate":{"value":0.9341000150093131},"critDamage":{"value":2.1715999951758675},"anemoDamageBonus":{"value":0.46600000691}},"talentsLevelMap":{"normalAttacks":{"icon":"https://enka.network/ui/Skill_A_03.png","level":10,"rawLevel":10,"id":10261,"boosted":false},"elementalSkill":{"icon":"https://enka.network/ui/Skill_S_Xiao_01.png","level":10,"rawLevel":10,"id":10262,"boosted":false},"elementalBurst":{"icon":"https://enka.network/ui/Skill_E_Xiao_01.png","level":10,"rawLevel":10,"id":10265,"boosted":false}},"weapon":{"weaponInfo":{"level":90,"promoteLevel":6,"refinementLevel":{"value":0}},"flat":{"icon":{"value":"UI_EquipIcon_Pole_Homa"}},"name":"Staff of Homa","icon":"https://enka.network/ui/UI_EquipIcon_Pole_Homa_Awaken.png"},"icon":"https://enka.network/ui/UI_AvatarIcon_Xiao.png","index":357,"nameCardLink":"https://enka.network/ui/UI_NameCardPic_Xiao_P.png","profilePictureLink":"https://enka.network/ui/UI_AvatarIcon_Xiao.png","characterMetadata":{"element":"Anemo"}},{"_id":"64ea59acdbe6a10bf2adf245","calculation":{"id":"1000002601","result":674834.5744351356},"characterId":10000026,"type":"current","uid":"110048484","artifactObjects":{"EQUIP_SHOES":{"mainStatKey":"ATK%"},"EQUIP_RING":{"mainStatKey":"Anemo DMG Bonus"},"EQUIP_DRESS":{"mainStatKey":"Crit RATE"}},"artifactSets":{"Vermillion Hereafter":{"icon":"https://enka.network/ui/UI_RelicIcon_15023_4.png","count":4},"Viridescent Venerer":{"icon":"https://enka.network/ui/UI_RelicIcon_15002_4.png","count":1}},"constellation":6,"costumeId":"","critValue":235.55999747698564,"md5":"66746150470f13dcf27fb115b09624ea","name":"Xiao","owner":{"nickname":"查無此人","adventureRank":60.0000007477,"profilePicture":10000005,"nameCard":"UI_NameCardPic_Yae1_P","patreon":{},"region":"CN"},"propMap":{"ascension":{"val":"6"},"level":{"val":"90"}},"proudSkillExtraLevelMap":{"2632":3,"2639":3},"stats":{"maxHp":{"value":21419.01579139143},"atk":{"value":2492.1644715817783},"def":{"value":919.1594328014538},"elementalMastery":{"value":0},"energyRecharge":{"value":1.2007000228327647},"healingBonus":{"value":0},"critRate":{"value":0.9030000221551688},"critDamage":{"value":2.1951000056214953},"anemoDamageBonus":{"value":0.466000001607}},"talentsLevelMap":{"normalAttacks":{"icon":"https://enka.network/ui/Skill_A_03.png","level":10,"rawLevel":10,"id":10261,"boosted":false},"elementalSkill":{"icon":"https://enka.network/ui/Skill_S_Xiao_01.png","level":13,"rawLevel":10,"id":10262,"boosted":true},"elementalBurst":{"icon":"https://enka.network/ui/Skill_E_Xiao_01.png","level":13,"rawLevel":10,"id":10265,"boosted":true}},"weapon":{"weaponInfo":{"level":90,"promoteLevel":6,"refinementLevel":{"value":4}},"flat":{"icon":{"value":"UI_EquipIcon_Pole_Homa"}},"name":"Staff of Homa","icon":"https://enka.network/ui/UI_EquipIcon_Pole_Homa_Awaken.png"},"icon":"https://enka.network/ui/UI_AvatarIcon_Xiao.png","index":358,"nameCardLink":"https://enka.network/ui/UI_NameCardPic_Yae1_P.png","profilePictureLink":"https://enka.network/ui/UI_AvatarIcon_PlayerBoy.png","characterMetadata":{"element":"Anemo"}},{"_id":"655cd12adbe6a10bf286d4c5","calculation":{"id":"1000002601","result":674827.8319678054,"additional":[{"name":"E Avg DMG","value":22396.84125174568,"quantity":1,"type":"E"},{"name":"E Avg DMG","value":24688.468933461718,"quantity":1,"type":"E"},{"name":"NA Avg DMG","value":4193.218778096526,"quantity":1,"type":"NA"},{"name":"Collision Plunge Avg DMG","value":14303.041351444625,"quantity":1,"type":"P"},{"name":"High Plunge Avg DMG","value":35724.00325674244,"quantity":1,"type":"P"},{"name":"NA Avg DMG","value":4496.833793738153,"quantity":1,"type":"NA"},{"name":"Collision Plunge Avg DMG","value":14802.764234332184,"quantity":1,"type":"P"},{"name":"High Plunge Avg DMG","value":36972.13653532943,"quantity":1,"type":"P"},{"name":"Collision Plunge Avg DMG","value":15302.487117219749,"quantity":1,"type":"P"},{"name":"High Plunge Avg DMG","value":40268.00607159738,"quantity":1,"type":"P"},{"name":"Collision Plunge Avg DMG","value":16122.352017577328,"quantity":1,"type":"P"},{"name":"High Plunge Avg DMG","value":40268.00607159738,"quantity":1,"type":"P"},{"name":"Collision Plunge Avg DMG","value":16122.352017577328,"quantity":1,"type":"P"},{"name":"High Plunge Avg DMG","value":40268.00607159738,"quantity":1,"type":"P"},{"name":"Collision Plunge Avg DMG","value":16122.352017577328,"quantity":1,"type":"P"},{"name":"High Plunge Avg DMG","value":41067.60905069133,"quantity":1,"type":"P"},{"name":"Collision Plunge Avg DMG","value":16442.49403504735,"quantity":1,"type":"P"},{"name":"High Plunge Avg DMG","value":41067.60905069133,"quantity":1,"type":"P"},{"name":"Collision Plunge Avg DMG","value":16442.49403504735,"quantity":1,"type":"P"},{"name":"High Plunge Avg DMG","value":41067.60905069133,"quantity":1,"type":"P"},{"name":"Collision Plunge Avg DMG","value":16762.636052517373,"quantity":1,"type":"P"},{"name":"High Plunge Avg DMG","value":41867.21202978529,"quantity":1,"type":"P"},{"name":"Collision Plunge Avg DMG","value":16762.636052517373,"quantity":1,"type":"P"},{"name":"High Plunge Avg DMG","value":41867.21202978529,"quantity":1,"type":"P"},{"name":"Collision Plunge Avg DMG","value":16762.636052517373,"quantity":1,"type":"P"},{"name":"High Plunge Avg DMG","value":42666.81500887924,"quantity":1,"type":"P"}]},"characterId":10000026,"type":"current","uid":"705158840","artifactObjects":{"EQUIP_SHOES":{"mainStatKey":"ATK%"},"EQUIP_RING":{"mainStatKey":"Anemo DMG Bonus"},"EQUIP_DRESS":{"mainStatKey":"Crit RATE"}},"artifactSets":{"Vermillion Hereafter":{"icon":"https://enka.network/ui/UI_RelicIcon_15023_4.png","count":4},"Wanderer's Troupe":{"icon":"https://enka.network/ui/UI_RelicIcon_15003_4.png","count":1}},"constellation":0,"costumeId":"","critValue":232.41999678188276,"md5":"99e4c1ba2c40e43855220b945c94538d","name":"Xiao","owner":{"nickname":"NX","adventureRank":60.0000001969,"profilePicture":{"characterId":10000026,"id":"","assets":{"icon":"UI_AvatarIcon_Xiao","sideIcon":"UI_AvatarIcon_Side_Xiao","gachaIcon":"UI_Gacha_AvatarImg_Xiao","constellations":["UI_Talent_S_Xiao_01","UI_Talent_S_Xiao_02","UI_Talent_U_Xiao_01","UI_Talent_S_Xiao_03","UI_Talent_U_Xiao_02","UI_Talent_S_Xiao_04"],"talents":{"normalAttack":"Skill_A_03","elementalSkill":"Skill_S_Xiao_01","elementalBurst":"Skill_E_Xiao_01"},"costumes":[]},"name":null},"nameCard":"UI_NameCardPic_Neuvillette_P","patreon":{},"region":"EU","enkaOwner":{}},"propMap":{"ascension":{"val":"6"},"level":{"val":"90"}},"proudSkillExtraLevelMap":{},"stats":{"maxHp":{"value":20731.52341163447},"atk":{"value":2567.597926234222},"def":{"value":892.2852651321348},"elementalMastery":{"value":23.309999713142382},"energyRecharge":{"value":1.272000014115081},"healingBonus":{"value":0},"critRate":{"value":0.8135000110814713},"critDamage":{"value":2.342699981293885},"anemoDamageBonus":{"value":0.466000002778}},"talentsLevelMap":{"normalAttacks":{"icon":"https://enka.network/ui/Skill_A_03.png","level":10,"rawLevel":10,"id":10261,"boosted":false},"elementalSkill":{"icon":"https://enka.network/ui/Skill_S_Xiao_01.png","level":10,"rawLevel":10,"id":10262,"boosted":false},"elementalBurst":{"icon":"https://enka.network/ui/Skill_E_Xiao_01.png","level":10,"rawLevel":10,"id":10265,"boosted":false}},"weapon":{"weaponInfo":{"level":90,"promoteLevel":6,"refinementLevel":{"value":0}},"flat":{"icon":{"value":"UI_EquipIcon_Pole_Homa"}},"name":"Staff of Homa","icon":"https://enka.network/ui/UI_EquipIcon_Pole_Homa_Awaken.png"},"lastBuildUpdate":1725799693530,"sortableType":"xiao","icon":"https://enka.network/ui/UI_AvatarIcon_Xiao.png","index":359,"nameCardLink":"https://enka.network/ui/UI_NameCardPic_Neuvillette_P.png","profilePictureLink":"https://enka.network/ui/UI_AvatarIcon_Xiao.png","characterMetadata":{"element":"Anemo"}},{"_id":"64ea5953dbe6a10bf2ac2347","calculation":{"id":"1000002601","result":674774.8186697598,"additional":[{"name":"E Avg DMG","value":22444.927413297457,"quantity":1,"type":"E"},{"name":"E Avg DMG","value":24741.475230344364,"quantity":1,"type":"E"},{"name":"NA Avg DMG","value":4200.117342586575,"quantity":1,"type":"NA"},{"name":"Collision Plunge Avg DMG","value":14318.164367331856,"quantity":1,"type":"P"},{"name":"High Plunge Avg DMG","value":35761.77527008788,"quantity":1,"type":"P"},{"name":"NA Avg DMG","value":4499.123471096503,"quantity":1,"type":"NA"},{"name":"Collision Plunge Avg DMG","value":14810.301438432442,"quantity":1,"type":"P"},{"name":"High Plunge Avg DMG","value":36990.961839487354,"quantity":1,"type":"P"},{"name":"Collision Plunge Avg DMG","value":15302.43850953303,"quantity":1,"type":"P"},{"name":"High Plunge Avg DMG","value":40248.551649545334,"quantity":1,"type":"P"},{"name":"Collision Plunge Avg DMG","value":16114.56292963332,"quantity":1,"type":"P"},{"name":"High Plunge Avg DMG","value":40248.551649545334,"quantity":1,"type":"P"},{"name":"Collision Plunge Avg DMG","value":16114.56292963332,"quantity":1,"type":"P"},{"name":"High Plunge Avg DMG","value":40248.551649545334,"quantity":1,"type":"P"},{"name":"Collision Plunge Avg DMG","value":16114.56292963332,"quantity":1,"type":"P"},{"name":"High Plunge Avg DMG","value":41047.76832080437,"quantity":1,"type":"P"},{"name":"Collision Plunge Avg DMG","value":16434.55027863303,"quantity":1,"type":"P"},{"name":"High Plunge Avg DMG","value":41047.76832080437,"quantity":1,"type":"P"},{"name":"Collision Plunge Avg DMG","value":16434.55027863303,"quantity":1,"type":"P"},{"name":"High Plunge Avg DMG","value":41047.76832080437,"quantity":1,"type":"P"},{"name":"Collision Plunge Avg DMG","value":16754.537627632733,"quantity":1,"type":"P"},{"name":"High Plunge Avg DMG","value":41846.9849920634,"quantity":1,"type":"P"},{"name":"Collision Plunge Avg DMG","value":16754.537627632733,"quantity":1,"type":"P"},{"name":"High Plunge Avg DMG","value":41846.9849920634,"quantity":1,"type":"P"},{"name":"Collision Plunge Avg DMG","value":16754.537627632733,"quantity":1,"type":"P"},{"name":"High Plunge Avg DMG","value":42646.20166332242,"quantity":1,"type":"P"}]},"characterId":10000026,"type":"current","uid":"800642954","artifactObjects":{"EQUIP_SHOES":{"mainStatKey":"ATK%"},"EQUIP_RING":{"mainStatKey":"Anemo DMG Bonus"},"EQUIP_DRESS":{"mainStatKey":"Crit RATE"}},"artifactSets":{"Vermillion Hereafter":{"icon":"https://enka.network/ui/UI_RelicIcon_15023_4.png","count":4},"Blizzard Strayer":{"icon":"https://enka.network/ui/UI_RelicIcon_14001_4.png","count":1}},"constellation":6,"costumeId":"","critValue":222.32999753657964,"md5":"cab095bb2de719bb51824cc23cdda9bd","name":"Xiao","owner":{"nickname":"しのぶ","adventureRank":60.0000008518,"profilePicture":{"characterId":10000065,"id":"","assets":{"icon":"UI_AvatarIcon_Shinobu","sideIcon":"UI_AvatarIcon_Side_Shinobu","gachaIcon":"UI_Gacha_AvatarImg_Shinobu","constellations":["UI_Talent_S_Shinobu_01","UI_Talent_S_Shinobu_02","UI_Talent_U_Shinobu_01","UI_Talent_S_Shinobu_03","UI_Talent_U_Shinobu_02","UI_Talent_S_Shinobu_04"],"talents":{"normalAttack":"Skill_A_01","elementalSkill":"Skill_S_Shinobu_01","elementalBurst":"Skill_E_Shinobu_01"},"costumes":[]},"name":null},"nameCard":"UI_NameCardPic_Shinobu_P","patreon":{},"region":"ASIA","enkaOwner":{}},"propMap":{"ascension":{"val":"6"},"level":{"val":"90"}},"proudSkillExtraLevelMap":{"2632":3,"2639":3},"stats":{"maxHp":{"value":20731.523439550947},"atk":{"value":2612.772557365937},"def":{"value":836.3265469417456},"elementalMastery":{"value":0},"energyRecharge":{"value":1.4729000282560991},"healingBonus":{"value":0},"critRate":{"value":0.8991000245993015},"critDamage":{"value":2.070600001398194},"anemoDamageBonus":{"value":0.466000005314}},"talentsLevelMap":{"normalAttacks":{"icon":"https://enka.network/ui/Skill_A_03.png","level":10,"rawLevel":10,"id":10261,"boosted":false},"elementalSkill":{"icon":"https://enka.network/ui/Skill_S_Xiao_01.png","level":13,"rawLevel":10,"id":10262,"boosted":true},"elementalBurst":{"icon":"https://enka.network/ui/Skill_E_Xiao_01.png","level":13,"rawLevel":10,"id":10265,"boosted":true}},"weapon":{"weaponInfo":{"level":90,"promoteLevel":6,"refinementLevel":{"value":4}},"flat":{"icon":{"value":"UI_EquipIcon_Pole_Homa"}},"name":"Staff of Homa","icon":"https://enka.network/ui/UI_EquipIcon_Pole_Homa_Awaken.png"},"lastBuildUpdate":1730622286366,"sortableType":"xiao","icon":"https://enka.network/ui/UI_AvatarIcon_Xiao.png","index":360,"nameCardLink":"https://enka.network/ui/UI_NameCardPic_Shinobu_P.png","profilePictureLink":"https://enka.network/ui/UI_AvatarIcon_Shinobu.png","characterMetadata":{"element":"Anemo"}}],"totalRowsHash":"b0364d65e3ac6e6a81b9bf030a3a2538"}
