{"playerInfo":{"nickname":"suiKING","level":60,"signature":"what","worldLevel":9,"nameCardId":210189,"finishAchievementNum":862,"towerFloorIndex":12,"towerLevelIndex":3,"showAvatarInfoList":[{"avatarId":10000060,"level":90,"energyType":2},{"avatarId":10000047,"level":90,"energyType":7}],"profilePicture":{"id":2000},"fetterCount":17,"towerStarIndex":36},"avatarInfoList":[{"avatarId":10000060,"propMap":{"1001":{"type":1001,"ival":"0"},"1002":{"type":1002,"ival":"6","val":"6"},"1003":{"type":1003,"ival":"0"},"1004":{"type":1004,"ival":"0"},"4001":{"type":4001,"ival":"90","val":"90"},"10010":{"type":10010,"ival":"24000","val":"24000"},"10049":{"type":10049,"ival":"12000","val":"12000"}},"fightPropMap":{"1":14450.17578125,"2":6004.8896484375,"3":0.16910000145435333,"4":753.56787109375,"5":361.58001708984375,"7":547.9793090820312,"8":37.029998779296875,"20":0.9570399522781372,"21":0,"22":1.5648999214172363,"23":1.3166000843048096,"26":0,"27":0,"28":0,"29":0,"30":0,"40":0,"41":0,"42":0.4659999907016754,"43":0,"44":0,"45":0,"46":0,"50":0,"51":0,"52":0,"53":0,"54":0,"55":0,"56":0,"72":70,"1002":64.6286392211914,"1010":22454.24609375,"2000":22898.58984375,"2001":1115.14794921875,"2002":585.00927734375,"2003":0,"2004":0,"3045":0,"3046":1},"skillDepotId":6001,"inherentProudSkillList":[602101,602201,602301],"skillLevelMap":{"10606":3,"10607":8,"10610":10},"equipList":[{"itemId":94544,"reliquary":{"level":21,"mainPropId":14001,"appendPropIdList":[501204,501234,501222,501083,501203,501203,501081,501203,501224]},"flat":{"nameTextMapHash":"600966780","rankLevel":5,"itemType":"ITEM_RELIQUARY","icon":"UI_RelicIcon_15020_4","equipType":"EQUIP_BRACER","setNameTextMapHash":"2276480763","reliquarySubstats":[{"appendPropId":"FIGHT_PROP_CRITICAL","statValue":14.4},{"appendPropId":"FIGHT_PROP_CHARGE_EFFICIENCY","statValue":6.5},{"appendPropId":"FIGHT_PROP_CRITICAL_HURT","statValue":14},{"appendPropId":"FIGHT_PROP_DEFENSE","statValue":37}],"reliquaryMainstat":{"mainPropId":"FIGHT_PROP_HP","statValue":4780}}},{"itemId":94524,"reliquary":{"level":21,"mainPropId":12001,"appendPropIdList":[501022,501232,501202,501223,501224,501224,501023,501202,501204]},"flat":{"nameTextMapHash":"481604708","rankLevel":5,"itemType":"ITEM_RELIQUARY","icon":"UI_RelicIcon_15020_2","equipType":"EQUIP_NECKLACE","setNameTextMapHash":"2276480763","reliquarySubstats":[{"appendPropId":"FIGHT_PROP_HP","statValue":508},{"appendPropId":"FIGHT_PROP_CHARGE_EFFICIENCY","statValue":5.2},{"appendPropId":"FIGHT_PROP_CRITICAL","statValue":10.1},{"appendPropId":"FIGHT_PROP_CRITICAL_HURT","statValue":22.5}],"reliquaryMainstat":{"mainPropId":"FIGHT_PROP_ATTACK","statValue":311}}},{"itemId":71513,"reliquary":{"level":21,"mainPropId":15011,"appendPropIdList":[501224,501034,501022,501201,501201,501203,501023,501203]},"flat":{"nameTextMapHash":"3716289628","rankLevel":5,"itemType":"ITEM_RELIQUARY","icon":"UI_RelicIcon_14001_1","equipType":"EQUIP_RING","setNameTextMapHash":"933076627","reliquarySubstats":[{"appendPropId":"FIGHT_PROP_CRITICAL_HURT","statValue":7.8},{"appendPropId":"FIGHT_PROP_HP_PERCENT","statValue":5.8},{"appendPropId":"FIGHT_PROP_HP","statValue":508},{"appendPropId":"FIGHT_PROP_CRITICAL","statValue":12.4}],"reliquaryMainstat":{"mainPropId":"FIGHT_PROP_WATER_ADD_HURT","statValue":46.6}}},{"itemId":94533,"reliquary":{"level":21,"mainPropId":13008,"appendPropIdList":[501053,501202,501021,501034,501051,501054,501204,501033]},"flat":{"nameTextMapHash":"1804680132","rankLevel":5,"itemType":"ITEM_RELIQUARY","icon":"UI_RelicIcon_15020_3","equipType":"EQUIP_DRESS","setNameTextMapHash":"2276480763","reliquarySubstats":[{"appendPropId":"FIGHT_PROP_ATTACK","statValue":51},{"appendPropId":"FIGHT_PROP_CRITICAL","statValue":7},{"appendPropId":"FIGHT_PROP_HP","statValue":209},{"appendPropId":"FIGHT_PROP_HP_PERCENT","statValue":11.1}],"reliquaryMainstat":{"mainPropId":"FIGHT_PROP_CRITICAL_HURT","statValue":62.2}}},{"itemId":15409,"weapon":{"level":90,"promoteLevel":6,"affixMap":{"115409":0}},"flat":{"nameTextMapHash":"3439749859","rankLevel":4,"itemType":"ITEM_WEAPON","icon":"UI_EquipIcon_Bow_Viridescent","weaponStats":[{"appendPropId":"FIGHT_PROP_BASE_ATTACK","statValue":510},{"appendPropId":"FIGHT_PROP_CRITICAL","statValue":27.6}]}}],"fetterInfo":{"expLevel":10}},{"avatarId":10000047,"propMap":{"1001":{"type":1001,"ival":"0"},"1002":{"type":1002,"ival":"6","val":"6"},"1003":{"type":1003,"ival":"0"},"1004":{"type":1004,"ival":"0"},"4001":{"type":4001,"ival":"90","val":"90"},"10010":{"type":10010,"ival":"24000","val":"24000"},"10049":{"type":10049,"ival":"12000","val":"12000"}},"fightPropMap":{"1":13348.04296875,"2":5198.259765625,"3":0.09910000115633011,"4":904.6558837890625,"5":347.9599914550781,"6":0.2797999978065491,"7":806.9820556640625,"8":41.65999984741211,"9":0.21140000224113464,"20":0.3144000172615051,"21":0,"22":0.7563999891281128,"23":1.3044999837875366,"24":0.10000000149011612,"26":0,"27":0,"28":1034.0107421875,"29":0,"30":0,"40":0,"41":0,"42":0,"43":0,"44":0.15000000596046448,"45":0,"46":0,"50":0,"51":0,"52":0,"53":0,"54":0,"55":0,"56":0,"74":60,"1004":43.04850769042969,"1010":19090.998046875,"2000":19869.09375,"2001":1505.738525390625,"2002":1019.238037109375,"2003":0,"2004":0,"2005":0,"3006":0,"3007":0,"3015":0,"3016":0,"3017":0,"3018":0,"3019":0,"3020":0,"3021":0,"3045":0,"3046":1},"skillDepotId":4701,"inherentProudSkillList":[472101,472201,472301],"skillLevelMap":{"10471":8,"10472":6,"10475":8},"equipList":[{"itemId":76544,"reliquary":{"level":21,"mainPropId":14001,"appendPropIdList":[501244,501053,501204,501034,501054,501242,501242,501243,501031]},"flat":{"nameTextMapHash":"2411209276","rankLevel":5,"itemType":"ITEM_RELIQUARY","icon":"UI_RelicIcon_15002_4","equipType":"EQUIP_BRACER","setNameTextMapHash":"1562601179","reliquarySubstats":[{"appendPropId":"FIGHT_PROP_ELEMENT_MASTERY","statValue":82},{"appendPropId":"FIGHT_PROP_ATTACK","statValue":37},{"appendPropId":"FIGHT_PROP_CRITICAL","statValue":3.9},{"appendPropId":"FIGHT_PROP_HP_PERCENT","statValue":9.9}],"reliquaryMainstat":{"mainPropId":"FIGHT_PROP_HP","statValue":4780}}},{"itemId":80524,"reliquary":{"level":21,"mainPropId":12001,"appendPropIdList":[501021,501234,501244,501063,501241,501061,501243,501242,501021]},"flat":{"nameTextMapHash":"4289008364","rankLevel":5,"itemType":"ITEM_RELIQUARY","icon":"UI_RelicIcon_15006_2","equipType":"EQUIP_NECKLACE","setNameTextMapHash":"1524173875","reliquarySubstats":[{"appendPropId":"FIGHT_PROP_HP","statValue":418},{"appendPropId":"FIGHT_PROP_CHARGE_EFFICIENCY","statValue":6.5},{"appendPropId":"FIGHT_PROP_ELEMENT_MASTERY","statValue":79},{"appendPropId":"FIGHT_PROP_ATTACK_PERCENT","statValue":9.3}],"reliquaryMainstat":{"mainPropId":"FIGHT_PROP_ATTACK","statValue":311}}},{"itemId":76553,"reliquary":{"level":21,"mainPropId":10008,"appendPropIdList":[501221,501064,501083,501204,501201,501062,501221,501204]},"flat":{"nameTextMapHash":"3520684620","rankLevel":5,"itemType":"ITEM_RELIQUARY","icon":"UI_RelicIcon_15002_5","equipType":"EQUIP_SHOES","setNameTextMapHash":"1562601179","reliquarySubstats":[{"appendPropId":"FIGHT_PROP_CRITICAL_HURT","statValue":10.9},{"appendPropId":"FIGHT_PROP_ATTACK_PERCENT","statValue":10.5},{"appendPropId":"FIGHT_PROP_DEFENSE","statValue":21},{"appendPropId":"FIGHT_PROP_CRITICAL","statValue":10.5}],"reliquaryMainstat":{"mainPropId":"FIGHT_PROP_ELEMENT_MASTERY","statValue":187}}},{"itemId":76513,"reliquary":{"level":21,"mainPropId":15007,"appendPropIdList":[501061,501201,501234,501223,501061,501202,501224,501201]},"flat":{"nameTextMapHash":"2114829356","rankLevel":5,"itemType":"ITEM_RELIQUARY","icon":"UI_RelicIcon_15002_1","equipType":"EQUIP_RING","setNameTextMapHash":"1562601179","reliquarySubstats":[{"appendPropId":"FIGHT_PROP_ATTACK_PERCENT","statValue":8.2},{"appendPropId":"FIGHT_PROP_CRITICAL","statValue":8.6},{"appendPropId":"FIGHT_PROP_CHARGE_EFFICIENCY","statValue":6.5},{"appendPropId":"FIGHT_PROP_CRITICAL_HURT","statValue":14.8}],"reliquaryMainstat":{"mainPropId":"FIGHT_PROP_ELEMENT_MASTERY","statValue":187}}},{"itemId":76533,"reliquary":{"level":21,"mainPropId":13010,"appendPropIdList":[501233,501203,501083,501094,501093,501094,501233,501233]},"flat":{"nameTextMapHash":"2442374844","rankLevel":5,"itemType":"ITEM_RELIQUARY","icon":"UI_RelicIcon_15002_3","equipType":"EQUIP_DRESS","setNameTextMapHash":"1562601179","reliquarySubstats":[{"appendPropId":"FIGHT_PROP_CHARGE_EFFICIENCY","statValue":17.5},{"appendPropId":"FIGHT_PROP_CRITICAL","statValue":3.5},{"appendPropId":"FIGHT_PROP_DEFENSE","statValue":21},{"appendPropId":"FIGHT_PROP_DEFENSE_PERCENT","statValue":21.1}],"reliquaryMainstat":{"mainPropId":"FIGHT_PROP_ELEMENT_MASTERY","statValue":187}}},{"itemId":11503,"weapon":{"level":90,"promoteLevel":6,"affixMap":{"111503":0}},"flat":{"nameTextMapHash":"2949448555","rankLevel":5,"itemType":"ITEM_WEAPON","icon":"UI_EquipIcon_Sword_Widsith","weaponStats":[{"appendPropId":"FIGHT_PROP_BASE_ATTACK","statValue":608},{"appendPropId":"FIGHT_PROP_ELEMENT_MASTERY","statValue":198}]}}],"fetterInfo":{"expLevel":10}}],"ttl":60,"uid":"832423608"}
